Proyecto2/Proyecto2.v
//memoria RAM de 4K*4 que se pueda leer y escribir
module RAM (input wire cs, wen, input wire [11:0]address, inout [3:0]data);
  reg [3:0]ram[0:4095];
  reg [3:0]data_out;
  //para sacar el output es necesario que el enable de escritura este en 0, el chipselect en 1 y el output en 1
  assign data = (cs &! wen)? data_out:4'bz;
  //ciclo always para escribir
  always @(address or data or cs or wen)begin;
    if (cs & wen) begin
        ram[address] = data;
        end
      end
  //ciclo para leer
  always @(address or cs)begin;
    if (cs &! wen) begin
      data_out = ram[address];
      end
      end
      endmodule
//toggle flip flop, que funciona como phase
module PHASE (input wire clock, reset, output reg Q);
  always @ (posedge clock or posedge reset) begin
    if (reset)begin
    Q <= 1'b0;
    end
    else begin
    Q <= ~Q;
    end
    end
  endmodule
//bufer tri estado de 4 bits
module BUS_DRIVER1 (input wire [3:0]in, input wire enable, output wire [3:0]out);
  assign out = enable? in: 4'bz;
  endmodule
//buffer tri estado para los inputs
module INPUTS  (input wire [3:0]in, input wire enable, output wire [3:0]out);
  assign out = enable? in: 4'bz;
  endmodule
//bufer tri estado de 4 bits
module BUS_DRIVER2 (input wire [3:0]in, input wire enable, output wire [3:0]out);
  assign out = enable? in: 4'bz;
  endmodule
//modulo del microcode implementado con cases
module DECODE (input wire [6:0]INPUT, output reg [12:0]OUTPUT);
    always @ (INPUT)begin
    casex(INPUT)
    7'bxxxxxx0: //0
    OUTPUT <= 13'b1000000001000;
    7'b00001x1://1
    OUTPUT <= 13'b0100000001000;
    7'b00000x1://2
    OUTPUT <= 13'b1000000001000;
    7'b00011x1://3
    OUTPUT <= 13'b1000000001000;
    7'b00010x1://4
    OUTPUT <= 13'b0100000001000;
    7'b0010xx1://5
    OUTPUT <= 13'b0001001000010;
    7'b0011xx1://6
    OUTPUT <= 13'b1001001100000;
    7'b0100xx1://7
    OUTPUT <= 13'b0011010000010;
    7'b0101xx1://8
    OUTPUT <= 13'b0011010000100;
    7'b0110xx1://9
    OUTPUT <= 13'b1011010100000;
    7'b0111xx1: //10
    OUTPUT <= 13'b1000000111000;
    7'b1000x11: //11
    OUTPUT <= 13'b0100000001000;
    7'b1000x01: //12
    OUTPUT <= 13'b1000000001000;
    7'b1001x11: //13
    OUTPUT <= 13'b1000000001000;
    7'b1001x01: //14
    OUTPUT <= 13'b0100000001000;
    7'b1010xx1: //15
    OUTPUT <= 13'b0011011000010;
    7'b1011xx1: //16
    OUTPUT <= 13'b1011011100000;
    7'b1100xx1: //17
    OUTPUT <= 13'b0100000001000;
    7'b1101xx1: //18
    OUTPUT <= 13'b0000000001001;
    7'b1110xx1: //19
    OUTPUT <= 13'b0011100000010;
    7'b1111xx1: //20
    OUTPUT <= 13'b1011100100000;
    default:
      OUTPUT <= 13'b0;
    endcase
    end
    endmodule
//modulo de contador con enable reset y clock, tiene la opcion de cargar el valor del load_1 al count al momento de activar el bit load o que load_1 tenga un cambio
module PC (input wire clock, reset, load, en, input wire [11:0]load_1, output reg [11:0]count);
  always @ (posedge clock or posedge reset) begin
      if (reset) begin
      count <= 12'b000000000000;
      end
      else if (load) begin
      count <= load_1;
      end
      else if (en) begin
      count <= count + 12'b000000000001;
      end
      end
    endmodule
//arreglo de memoria de 4kx8bits a la cual cargue los valores ingresados en ROM.list
module ROM (input wire[11:0]address, output wire [7:0]palabra);
  reg [7:0] array [0:4095];
    initial begin
    $readmemh("ROM_proyecto.list", array);
    end
    assign palabra = array[address];
    endmodule
//flip flop de 8 bits
module FETCH (input wire clock, reset, en, input wire [7:0]D, output reg [3:0]instr, operand);
  always @ (posedge clock or posedge reset) begin
    if (reset)begin
    {instr, operand} <= 8'b0;
    end
    else if (en) begin
    {instr, operand} <= D;
    end
    end
  endmodule
//flAGS
module FLAGS (input wire clock, reset, en, input wire [1:0]D, output reg [1:0]Q);
  always @ (posedge clock or posedge reset) begin
    if (reset)begin
    Q <= 2'b0;
    end
    else if (en) begin
    Q <= D;
    end
    end
  endmodule
//buffer triestado de 4 bits
module buffer (input wire [3:0]in, input wire enable, output wire [3:0]out);
  assign out = enable? in: 4'bz;
  endmodule
//acumulador, flip flop D de 4 bits
module ACCU (input wire clock, reset, en, input wire [3:0]D, output reg [3:0]Q);
  always @ (posedge clock or posedge reset or en) begin
    if (reset)begin
    Q <= 4'b0;
    end
    else if (en) begin
    Q <= D;
    end
    end
  endmodule
//outputs, flip flop D de 4 bits
module OUTPUTS (input wire clock, reset, en, input wire [3:0]D, output reg [3:0]Q);
  always @ (posedge clock or posedge reset) begin
    if (reset)begin
    Q <= 4'b0;
    end
    else if (en) begin
    Q <= D;
    end
    end
  endmodule
//alu implementada con cases
module ALU (input wire [3:0]A, B,input wire [2:0]s, output reg [3:0]OUT, output reg C,output wire Zero);
  assign Zero = (OUT == 4'b0)? 1'b1: 1'b0;
  always @ (*)begin
  case(s)
  3'b000:
  {C,OUT} <= A;
  3'b001:
  {C,OUT} <= A-B;
  3'b010:
  {C,OUT} <= B;
  3'b011:
  {C,OUT} <= A + B;
  3'b100:
  {C,OUT} <= ~({1'b1,A} & {1'b1,B});
  default:
  {C,OUT} <= 5'b0;
  endcase
  end
  endmodule
//MODULO FINAL
module uP (input wire clock, reset, input wire [3:0]pushbuttons, output wire phase, c_flag, z_flag, output wire [3:0]instr, oprnd, data_bus, FF_out, accu, output wire [7:0]program_byte, output wire [11:0]PC, address_RAM);
  wire incPC, loadPC, loadA, loadFlags, csRAM, weRAM, oeALU, oeIN, oeOprnd, loadOut,c_bandera, z_bandera;
  wire [2:0]S;
  wire [3:0]out_ALU;
  assign address_RAM = {oprnd,program_byte};
  FETCH fetch(clock, reset, ~phase, program_byte, instr, oprnd);
  PC ProgramC(clock, reset, loadPC, incPC, address_RAM, PC);
  ROM rom(PC, program_byte);
  BUS_DRIVER1 B1(oprnd, oeOprnd,data_bus);
  FLAGS flags(clock, reset, loadFlags,{c_bandera, z_bandera},{c_flag, z_flag});
  PHASE phse(clock, reset, phase);
  DECODE decode({instr,c_flag, z_flag,phase}, {incPC, loadPC, loadA, loadFlags,S, csRAM, weRAM,oeALU,oeIN, oeOprnd, loadOut});
  RAM ram(csRAM, weRAM,address_RAM, data_bus);
  ACCU accumulador (clock, reset,loadA,out_ALU, accu);
  ALU alu(accu, data_bus, S, out_ALU, c_bandera, z_bandera);
  BUS_DRIVER2 B2(out_ALU,oeALU, data_bus);
  INPUTS IN(pushbuttons, oeIN, data_bus);
  OUTPUTS OUT(clock, reset, loadOut, data_bus, FF_out);
  endmodule

Digital_1/Proyecto2/Proyecto2_tb.v
`include "Proyecto2.v"
module testbench();

    reg clock, reset;
    reg [3:0] pushbuttons;
    wire phase, c_flag, z_flag;
    wire [3:0] instr, oprnd, accu, data_bus, FF_out;
    wire [7:0] program_byte;
    wire [11:0] PC, address_RAM;
    uP uPmodule(.clock(clock), .reset(reset), .pushbuttons(pushbuttons), .phase(phase),.c_flag(c_flag),.z_flag(z_flag),.instr(instr),
                .oprnd(oprnd),.accu(accu),.data_bus(data_bus),.FF_out(FF_out),.program_byte(program_byte),.PC(PC),.address_RAM(address_RAM));
  always
    #5 clock <=~clock;

  initial begin
  clock = 0; reset = 0; pushbuttons = 4'b0110; 
  #2 reset = 1;
  #1 reset = 0;
  end
  initial
    #1000 $finish;
  initial begin
      $dumpfile("Proyecto2.vcd");
      $dumpvars(0, testbench);
    end
  endmodule

Digital_1/Proyecto2/Proyecto2.vcd
$date
	Sun Nov 22 10:35:26 2020
$end
$version
	Icarus Verilog
$end
$timescale
	1s
$end
$scope module testbench $end
$var wire 4 ! data_bus [3:0] $end
$var wire 1 " z_flag $end
$var wire 8 # program_byte [7:0] $end
$var wire 1 $ phase $end
$var wire 4 % oprnd [3:0] $end
$var wire 4 & instr [3:0] $end
$var wire 1 ' c_flag $end
$var wire 12 ( address_RAM [11:0] $end
$var wire 4 ) accu [3:0] $end
$var wire 12 * PC [11:0] $end
$var wire 4 + FF_out [3:0] $end
$var reg 1 , clock $end
$var reg 4 - pushbuttons [3:0] $end
$var reg 1 . reset $end
$scope module uPmodule $end
$var wire 1 , clock $end
$var wire 4 / data_bus [3:0] $end
$var wire 4 0 pushbuttons [3:0] $end
$var wire 1 . reset $end
$var wire 1 " z_flag $end
$var wire 1 1 z_bandera $end
$var wire 1 2 weRAM $end
$var wire 8 3 program_byte [7:0] $end
$var wire 1 $ phase $end
$var wire 4 4 out_ALU [3:0] $end
$var wire 4 5 oprnd [3:0] $end
$var wire 1 6 oeOprnd $end
$var wire 1 7 oeIN $end
$var wire 1 8 oeALU $end
$var wire 1 9 loadPC $end
$var wire 1 : loadOut $end
$var wire 1 ; loadFlags $end
$var wire 1 < loadA $end
$var wire 4 = instr [3:0] $end
$var wire 1 > incPC $end
$var wire 1 ? csRAM $end
$var wire 1 ' c_flag $end
$var wire 1 @ c_bandera $end
$var wire 12 A address_RAM [11:0] $end
$var wire 4 B accu [3:0] $end
$var wire 3 C S [2:0] $end
$var wire 12 D PC [11:0] $end
$var wire 4 E FF_out [3:0] $end
$scope module B1 $end
$var wire 1 6 enable $end
$var wire 4 F out [3:0] $end
$var wire 4 G in [3:0] $end
$upscope $end
$scope module B2 $end
$var wire 1 8 enable $end
$var wire 4 H out [3:0] $end
$var wire 4 I in [3:0] $end
$upscope $end
$scope module IN $end
$var wire 1 7 enable $end
$var wire 4 J in [3:0] $end
$var wire 4 K out [3:0] $end
$upscope $end
$scope module OUT $end
$var wire 4 L D [3:0] $end
$var wire 1 , clock $end
$var wire 1 : en $end
$var wire 1 . reset $end
$var reg 4 M Q [3:0] $end
$upscope $end
$scope module ProgramC $end
$var wire 1 , clock $end
$var wire 1 > en $end
$var wire 1 9 load $end
$var wire 12 N load_1 [11:0] $end
$var wire 1 . reset $end
$var reg 12 O count [11:0] $end
$upscope $end
$scope module accumulador $end
$var wire 1 , clock $end
$var wire 1 < en $end
$var wire 1 . reset $end
$var wire 4 P D [3:0] $end
$var reg 4 Q Q [3:0] $end
$upscope $end
$scope module alu $end
$var wire 4 R A [3:0] $end
$var wire 4 S B [3:0] $end
$var wire 3 T s [2:0] $end
$var wire 1 1 Zero $end
$var reg 1 @ C $end
$var reg 4 U OUT [3:0] $end
$upscope $end
$scope module decode $end
$var wire 7 V INPUT [6:0] $end
$var reg 13 W OUTPUT [12:0] $end
$upscope $end
$scope module fetch $end
$var wire 1 , clock $end
$var wire 1 X en $end
$var wire 1 . reset $end
$var wire 8 Y D [7:0] $end
$var reg 4 Z instr [3:0] $end
$var reg 4 [ operand [3:0] $end
$upscope $end
$scope module flags $end
$var wire 2 \ D [1:0] $end
$var wire 1 , clock $end
$var wire 1 ; en $end
$var wire 1 . reset $end
$var reg 2 ] Q [1:0] $end
$upscope $end
$scope module phse $end
$var wire 1 , clock $end
$var wire 1 . reset $end
$var reg 1 $ Q $end
$upscope $end
$scope module ram $end
$var wire 12 ^ address [11:0] $end
$var wire 1 ? cs $end
$var wire 4 _ data [3:0] $end
$var wire 1 2 wen $end
$var reg 4 ` data_out [3:0] $end
$upscope $end
$scope module rom $end
$var wire 12 a address [11:0] $end
$var wire 8 b palabra [7:0] $end
$upscope $end
$upscope $end
$upscope $end
$enddefinitions $end
#0
$dumpvars
bx b
bx a
bx `
bx _
bx ^
bx ]
bx \
bx [
bx Z
bx Y
xX
bx W
bx V
bx U
bx T
bx S
bx R
bx Q
bx P
bx O
bx N
bx M
bx L
bx K
b110 J
bx I
bx H
bx G
bx F
bx E
bx D
bx C
bx B
bx A
x@
x?
x>
bx =
x<
x;
x:
x9
x8
x7
x6
bx 5
bx 4
bx 3
x2
x1
b110 0
bx /
0.
b110 -
0,
bx +
bx *
bx )
bx (
x'
bx &
bx %
x$
bx #
x"
bx !
$end
#2
b0 !
b0 /
b0 F
b0 H
b0 K
b0 L
b0 S
b0 _
0:
06
07
18
02
0?
b0 C
b0 T
0;
0<
09
1>
11
b1000000001000 W
b1 \
0@
b0 4
b0 I
b0 P
b0 U
0"
0'
1X
b0 &
b0 =
b0 Z
b0 %
b0 5
b0 G
b0 [
b1001111 (
b1001111 A
b1001111 N
b1001111 ^
b1001111 #
b1001111 3
b1001111 Y
b1001111 b
b0 *
b0 D
b0 O
b0 a
b0 ]
b0 V
0$
b0 +
b0 E
b0 M
b0 )
b0 B
b0 Q
b0 R
1.
#3
0.
#5
b0 \
01
b1111 4
b1111 I
b1111 P
b1111 U
b1111 !
b1111 /
b1111 F
b1111 H
b1111 K
b1111 L
b1111 S
b1111 _
16
08
b10 C
b10 T
1;
1<
0>
b11010000010 W
0X
1$
b10100001 #
b10100001 3
b10100001 Y
b10100001 b
b1 *
b1 D
b1 O
b1 a
b100001 V
b100 &
b100 =
b100 Z
b111110100001 (
b111110100001 A
b111110100001 N
b111110100001 ^
b1111 %
b1111 5
b1111 G
b1111 [
1,
#10
0,
#15
06
18
b0 C
b0 T
0;
0<
1>
b1000000001000 W
1X
b100000 V
0$
b1111 )
b1111 B
b1111 Q
b1111 R
1,
#20
0,
#25
11
b11 \
1@
b0 4
b0 I
b0 P
b0 U
b1 !
b1 /
b1 F
b1 H
b1 K
b1 L
b1 S
b1 _
16
08
b11 C
b11 T
1;
1<
0>
b11011000010 W
0X
1$
b1000000 #
b1000000 3
b1000000 Y
b1000000 b
b10 *
b10 D
b10 O
b10 a
b1010001 V
b1010 &
b1010 =
b1010 Z
b101000000 (
b101000000 A
b101000000 N
b101000000 ^
b1 %
b1 5
b1 G
b1 [
1,
#30
0,
#35
b0 !
b0 /
b0 F
b0 H
b0 K
b0 L
b0 S
b0 _
06
18
b0 C
b0 T
0;
0<
1>
11
b1000000001000 W
b1 \
0@
b0 4
b0 I
b0 P
b0 U
1"
1'
1X
b11 ]
b1010110 V
0$
b0 )
b0 B
b0 Q
b0 R
1,
#40
0,
#45
b0 !
b0 /
b0 F
b0 H
b0 K
b0 L
b0 S
b0 _
16
08
b10 C
b10 T
1;
1<
0>
b11010000010 W
0X
1$
b1000001 #
b1000001 3
b1000001 Y
b1000001 b
b11 *
b11 D
b11 O
b11 a
b100111 V
b100 &
b100 =
b100 Z
b1000001 (
b1000001 A
b1000001 N
b1000001 ^
b0 %
b0 5
b0 G
b0 [
1,
#50
0,
#55
06
18
b0 C
b0 T
0;
0<
1>
b1000000001000 W
0'
1X
b1 ]
b100010 V
0$
1,
#60
0,
#65
b0 \
01
b1 4
b1 I
b1 P
b1 U
b1 !
b1 /
b1 F
b1 H
b1 K
b1 L
b1 S
b1 _
16
08
b10 C
b10 T
1;
1<
0>
b11010000010 W
0X
b100011 V
1$
b100001 #
b100001 3
b100001 Y
b100001 b
b100 *
b100 D
b100 O
b100 a
b100100001 (
b100100001 A
b100100001 N
b100100001 ^
b1 %
b1 5
b1 G
b1 [
1,
#70
0,
#75
06
18
b0 C
b0 T
0;
0<
1>
b1000000001000 W
0"
1X
b0 ]
b100000 V
0$
b1 )
b1 B
b1 Q
b1 R
1,
#80
0,
#85
b1 \
11
b0 4
b0 I
b0 P
b0 U
b1 !
b1 /
b1 F
b1 H
b1 K
b1 L
b1 S
b1 _
16
08
b1 C
b1 T
1;
0>
b1001000010 W
0X
1$
b111010000 (
b111010000 A
b111010000 N
b111010000 ^
b11010000 #
b11010000 3
b11010000 Y
b11010000 b
b101 *
b101 D
b101 O
b101 a
b10001 V
b10 &
b10 =
b10 Z
1,
#90
0,
#95
b0 \
01
b1 4
b1 I
b1 P
b1 U
b1 !
b1 /
b1 F
b1 H
b1 K
b1 L
b1 S
b1 _
06
18
b0 C
b0 T
0;
1>
b1000000001000 W
1"
1X
b1 ]
b10010 V
0$
1,
#100
0,
#105
1:
0>
b1001 W
0X
1$
b1000000 #
b1000000 3
b1000000 Y
b1000000 b
b110 *
b110 D
b110 O
b110 a
b1101011 V
b1101 &
b1101 =
b1101 Z
b1000000 (
b1000000 A
b1000000 N
b1000000 ^
b0 %
b0 5
b0 G
b0 [
1,
#110
0,
#115
0:
1>
b1000000001000 W
1X
b1101010 V
0$
b1 +
b1 E
b1 M
1,
#120
0,
#125
b1 \
11
b0 4
b0 I
b0 P
b0 U
b0 !
b0 /
b0 F
b0 H
b0 K
b0 L
b0 S
b0 _
16
08
b10 C
b10 T
1;
1<
0>
b11010000010 W
0X
1$
b11100000 (
b11100000 A
b11100000 N
b11100000 ^
b11100000 #
b11100000 3
b11100000 Y
b11100000 b
b111 *
b111 D
b111 O
b111 a
b100011 V
b100 &
b100 =
b100 Z
1,
#130
0,
#135
06
18
b0 C
b0 T
0;
0<
1>
b1000000001000 W
1X
b100010 V
0$
b0 )
b0 B
b0 Q
b0 R
1,
#140
0,
#145
b0 \
01
b1111 4
b1111 I
b1111 P
b1111 U
b0 !
b0 /
b0 F
b0 H
b0 K
b0 L
b0 S
b0 _
16
08
b100 C
b100 T
1;
1<
0>
b11100000010 W
0X
1$
b1010000 (
b1010000 A
b1010000 N
b1010000 ^
b1010000 #
b1010000 3
b1010000 Y
b1010000 b
b1000 *
b1000 D
b1000 O
b1000 a
b1110011 V
b1110 &
b1110 =
b1110 Z
1,
#150
0,
#155
b1111 !
b1111 /
b1111 F
b1111 H
b1111 K
b1111 L
b1111 S
b1111 _
06
18
b0 C
b0 T
0;
0<
1>
b1000000001000 W
0"
1X
b0 ]
b1110000 V
0$
b1111 )
b1111 B
b1111 Q
b1111 R
1,
#160
0,
#165
b110 4
b110 I
b110 P
b110 U
b110 !
b110 /
b110 F
b110 H
b110 K
b110 L
b110 S
b110 _
17
08
b10 C
b10 T
1;
1<
0>
b11010000100 W
0X
1$
b1000000 (
b1000000 A
b1000000 N
b1000000 ^
b1000000 #
b1000000 3
b1000000 Y
b1000000 b
b1001 *
b1001 D
b1001 O
b1001 a
b101001 V
b101 &
b101 =
b101 Z
1,
#170
0,
#175
07
18
b0 C
b0 T
0;
0<
1>
b1000000001000 W
1X
b101000 V
0$
b110 )
b110 B
b110 Q
b110 R
1,
#180
0,
#185
b1 \
11
b0 4
b0 I
b0 P
b0 U
b0 !
b0 /
b0 F
b0 H
b0 K
b0 L
b0 S
b0 _
16
08
b10 C
b10 T
1;
1<
0>
b11010000010 W
0X
1$
b10000000 (
b10000000 A
b10000000 N
b10000000 ^
b10000000 #
b10000000 3
b10000000 Y
b10000000 b
b1010 *
b1010 D
b1010 O
b1010 a
b100001 V
b100 &
b100 =
b100 Z
1,
#190
0,
#195
06
18
b0 C
b0 T
0;
0<
1>
b1000000001000 W
1"
1X
b1 ]
b100010 V
0$
b0 )
b0 B
b0 Q
b0 R
1,
#200
0,
#205
19
0>
b100000001000 W
0X
1$
b1111 (
b1111 A
b1111 N
b1111 ^
b1111 #
b1111 3
b1111 Y
b1111 b
b1011 *
b1011 D
b1011 O
b1011 a
b1000011 V
b1000 &
b1000 =
b1000 Z
1,
#210
0,
#215
09
1>
b1000000001000 W
1X
b1000001 (
b1000001 A
b1000001 N
b1000001 ^
b1000001 #
b1000001 3
b1000001 Y
b1000001 b
b1111 *
b1111 D
b1111 O
b1111 a
b1000010 V
0$
1,
#220
0,
#225
b0 \
01
b1 4
b1 I
b1 P
b1 U
b1 !
b1 /
b1 F
b1 H
b1 K
b1 L
b1 S
b1 _
16
08
b10 C
b10 T
1;
1<
0>
b11010000010 W
0X
1$
b10010000 #
b10010000 3
b10010000 Y
b10010000 b
b10000 *
b10000 D
b10000 O
b10000 a
b100011 V
b100 &
b100 =
b100 Z
b110010000 (
b110010000 A
b110010000 N
b110010000 ^
b1 %
b1 5
b1 G
b1 [
1,
#230
0,
#235
06
18
b0 C
b0 T
0;
0<
1>
b1000000001000 W
0"
1X
b0 ]
b100000 V
0$
b1 )
b1 B
b1 Q
b1 R
1,
#240
0,
#245
19
0>
b100000001000 W
0X
1$
b10100 #
b10100 3
b10100 Y
b10100 b
b10001 *
b10001 D
b10001 O
b10001 a
b1001001 V
b1001 &
b1001 =
b1001 Z
b10100 (
b10100 A
b10100 N
b10100 ^
b0 %
b0 5
b0 G
b0 [
1,
#250
0,
#255
09
1>
b1000000001000 W
1X
b1001111 (
b1001111 A
b1001111 N
b1001111 ^
b1001111 #
b1001111 3
b1001111 Y
b1001111 b
b10100 *
b10100 D
b10100 O
b10100 a
b1001000 V
0$
1,
#260
0,
#265
b1111 4
b1111 I
b1111 P
b1111 U
b1111 !
b1111 /
b1111 F
b1111 H
b1111 K
b1111 L
b1111 S
b1111 _
16
08
b10 C
b10 T
1;
1<
0>
b11010000010 W
0X
1$
b10100001 #
b10100001 3
b10100001 Y
b10100001 b
b10101 *
b10101 D
b10101 O
b10101 a
b100001 V
b100 &
b100 =
b100 Z
b111110100001 (
b111110100001 A
b111110100001 N
b111110100001 ^
b1111 %
b1111 5
b1111 G
b1111 [
1,
#270
0,
#275
06
18
b0 C
b0 T
0;
0<
1>
b1000000001000 W
1X
b100000 V
0$
b1111 )
b1111 B
b1111 Q
b1111 R
1,
#280
0,
#285
11
b11 \
1@
b0 4
b0 I
b0 P
b0 U
b1 !
b1 /
b1 F
b1 H
b1 K
b1 L
b1 S
b1 _
16
08
b11 C
b11 T
1;
1<
0>
b11011000010 W
0X
1$
b0 #
b0 3
b0 Y
b0 b
b10110 *
b10110 D
b10110 O
b10110 a
b1010001 V
b1010 &
b1010 =
b1010 Z
b100000000 (
b100000000 A
b100000000 N
b100000000 ^
b1 %
b1 5
b1 G
b1 [
1,
#290
0,
#295
b0 !
b0 /
b0 F
b0 H
b0 K
b0 L
b0 S
b0 _
06
18
b0 C
b0 T
0;
0<
1>
11
b1000000001000 W
b1 \
0@
b0 4
b0 I
b0 P
b0 U
1"
1'
1X
b11 ]
b1010110 V
0$
b0 )
b0 B
b0 Q
b0 R
1,
#300
0,
#305
19
0>
b100000001000 W
0X
1$
b11110 #
b11110 3
b11110 Y
b11110 b
b10111 *
b10111 D
b10111 O
b10111 a
b111 V
b0 &
b0 =
b0 Z
b11110 (
b11110 A
b11110 N
b11110 ^
b0 %
b0 5
b0 G
b0 [
1,
#310
0,
#315
09
1>
b1000000001000 W
1X
b1000001 (
b1000001 A
b1000001 N
b1000001 ^
b1000001 #
b1000001 3
b1000001 Y
b1000001 b
b11110 *
b11110 D
b11110 O
b11110 a
b110 V
0$
1,
#320
0,
#325
b0 \
01
b1 4
b1 I
b1 P
b1 U
b1 !
b1 /
b1 F
b1 H
b1 K
b1 L
b1 S
b1 _
16
08
b10 C
b10 T
1;
1<
0>
b11010000010 W
0X
1$
b10100001 #
b10100001 3
b10100001 Y
b10100001 b
b11111 *
b11111 D
b11111 O
b11111 a
b100111 V
b100 &
b100 =
b100 Z
b110100001 (
b110100001 A
b110100001 N
b110100001 ^
b1 %
b1 5
b1 G
b1 [
1,
#330
0,
#335
06
18
b0 C
b0 T
0;
0<
1>
b1000000001000 W
0"
0'
1X
b0 ]
b100000 V
0$
b1 )
b1 B
b1 Q
b1 R
1,
#340
0,
#345
b10 4
b10 I
b10 P
b10 U
b1 !
b1 /
b1 F
b1 H
b1 K
b1 L
b1 S
b1 _
16
08
b11 C
b11 T
1;
1<
0>
b11011000010 W
0X
1$
b100010000 (
b100010000 A
b100010000 N
b100010000 ^
b10000 #
b10000 3
b10000 Y
b10000 b
b100000 *
b100000 D
b100000 O
b100000 a
b1010001 V
b1010 &
b1010 =
b1010 Z
1,
#350
0,
#355
b10 !
b10 /
b10 F
b10 H
b10 K
b10 L
b10 S
b10 _
06
18
b0 C
b0 T
0;
0<
1>
b1000000001000 W
b10 4
b10 I
b10 P
b10 U
1X
b1010000 V
0$
b10 )
b10 B
b10 Q
b10 R
1,
#360
0,
#365
19
0>
b100000001000 W
0X
1$
b101000 #
b101000 3
b101000 Y
b101000 b
b100001 *
b100001 D
b100001 O
b100001 a
b1001 V
b1 &
b1 =
b1 Z
b101000 (
b101000 A
b101000 N
b101000 ^
b0 %
b0 5
b0 G
b0 [
1,
#370
0,
#375
09
1>
b1000000001000 W
1X
b1000001 (
b1000001 A
b1000001 N
b1000001 ^
b1000001 #
b1000001 3
b1000001 Y
b1000001 b
b101000 *
b101000 D
b101000 O
b101000 a
b1000 V
0$
1,
#380
0,
#385
b1 4
b1 I
b1 P
b1 U
b1 !
b1 /
b1 F
b1 H
b1 K
b1 L
b1 S
b1 _
16
08
b10 C
b10 T
1;
1<
0>
b11010000010 W
0X
1$
b11000000 #
b11000000 3
b11000000 Y
b11000000 b
b101001 *
b101001 D
b101001 O
b101001 a
b100001 V
b100 &
b100 =
b100 Z
b111000000 (
b111000000 A
b111000000 N
b111000000 ^
b1 %
b1 5
b1 G
b1 [
1,
#390
0,
#395
06
18
b0 C
b0 T
0;
0<
1>
b1000000001000 W
1X
b100000 V
0$
b1 )
b1 B
b1 Q
b1 R
1,
#400
0,
#405
19
0>
b100000001000 W
0X
1$
b1111111 #
b1111111 3
b1111111 Y
b1111111 b
b101010 *
b101010 D
b101010 O
b101010 a
b1100001 V
b1100 &
b1100 =
b1100 Z
b1111111 (
b1111111 A
b1111111 N
b1111111 ^
b0 %
b0 5
b0 G
b0 [
1,
#410
0,
#415
09
1>
b1000000001000 W
1X
b1000001 (
b1000001 A
b1000001 N
b1000001 ^
b1000001 #
b1000001 3
b1000001 Y
b1000001 b
b1111111 *
b1111111 D
b1111111 O
b1111111 a
b1100000 V
0$
1,
#420
0,
#425
b1 !
b1 /
b1 F
b1 H
b1 K
b1 L
b1 S
b1 _
16
08
b10 C
b10 T
1;
1<
0>
b11010000010 W
0X
1$
b1110000 #
b1110000 3
b1110000 Y
b1110000 b
b10000000 *
b10000000 D
b10000000 O
b10000000 a
b100001 V
b100 &
b100 =
b100 Z
b101110000 (
b101110000 A
b101110000 N
b101110000 ^
b1 %
b1 5
b1 G
b1 [
1,
#430
0,
#435
06
18
b0 C
b0 T
0;
0<
1>
b1000000001000 W
1X
b100000 V
0$
1,
#440
0,
#445
12
1?
b1000000111000 W
0X
1$
b0 #
b0 3
b0 Y
b0 b
b10000001 *
b10000001 D
b10000001 O
b10000001 a
b111001 V
b111 &
b111 =
b111 Z
b0 (
b0 A
b0 N
b0 ^
b0 %
b0 5
b0 G
b0 [
1,
#450
0,
#455
02
0?
b1000000001000 W
1X
b1100000 (
b1100000 A
b1100000 N
b1100000 ^
b1100000 #
b1100000 3
b1100000 Y
b1100000 b
b10000010 *
b10000010 D
b10000010 O
b10000010 a
b111000 V
0$
1,
#460
0,
#465
b1 !
b1 /
b1 F
b1 H
b1 K
b1 L
b1 S
b1 _
b1 `
08
1?
b10 C
b10 T
1;
1<
b1011010100000 W
0X
1$
b0 (
b0 A
b0 N
b0 ^
b0 #
b0 3
b0 Y
b0 b
b10000011 *
b10000011 D
b10000011 O
b10000011 a
b110001 V
b110 &
b110 =
b110 Z
1,
#470
0,
#475
b0 \
01
18
0?
b0 C
b0 T
0;
0<
b1 4
b1 I
b1 P
b1 U
b1000000001000 W
b1 !
b1 /
b1 F
b1 H
b1 K
b1 L
b1 S
b1 _
bx `
1X
b110000 (
b110000 A
b110000 N
b110000 ^
b110000 #
b110000 3
b110000 Y
b110000 b
b10000100 *
b10000100 D
b10000100 O
b10000100 a
b110000 V
0$
1,
#480
0,
#485
b1 \
11
b0 4
b0 I
b0 P
b0 U
b1 !
b1 /
b1 F
b1 H
b1 K
b1 L
b1 S
b1 _
b1 `
08
1?
b1 C
b1 T
1;
b1001001100000 W
0X
1$
b0 (
b0 A
b0 N
b0 ^
b0 #
b0 3
b0 Y
b0 b
b10000101 *
b10000101 D
b10000101 O
b10000101 a
b11001 V
b11 &
b11 =
b11 Z
1,
#490
0,
#495
01
18
0?
b0 C
b0 T
0;
b0 \
0@
b1 4
b1 I
b1 P
b1 U
b1000000001000 W
b1 !
b1 /
b1 F
b1 H
b1 K
b1 L
b1 S
b1 _
bx `
1"
1X
b10110000 (
b10110000 A
b10110000 N
b10110000 ^
b10110000 #
b10110000 3
b10110000 Y
b10110000 b
b10000110 *
b10000110 D
b10000110 O
b10000110 a
b1 ]
b11010 V
0$
1,
#500
0,
#505
b10 4
b10 I
b10 P
b10 U
b1 !
b1 /
b1 F
b1 H
b1 K
b1 L
b1 S
b1 _
b1 `
08
1?
b11 C
b11 T
1;
1<
b1011011100000 W
0X
1$
b0 (
b0 A
b0 N
b0 ^
b0 #
b0 3
b0 Y
b0 b
b10000111 *
b10000111 D
b10000111 O
b10000111 a
b1011011 V
b1011 &
b1011 =
b1011 Z
1,
#510
0,
#515
01
18
0?
b0 C
b0 T
0;
0<
b0 \
0@
b1000000001000 W
b10 4
b10 I
b10 P
b10 U
b10 !
b10 /
b10 F
b10 H
b10 K
b10 L
b10 S
b10 _
bx `
0"
1X
b1000000 (
b1000000 A
b1000000 N
b1000000 ^
b1000000 #
b1000000 3
b1000000 Y
b1000000 b
b10001000 *
b10001000 D
b10001000 O
b10001000 a
b0 ]
b1011000 V
0$
b10 )
b10 B
b10 Q
b10 R
1,
#520
0,
#525
b1 \
11
b0 4
b0 I
b0 P
b0 U
b0 !
b0 /
b0 F
b0 H
b0 K
b0 L
b0 S
b0 _
16
08
b10 C
b10 T
1;
1<
0>
b11010000010 W
0X
1$
b11110000 (
b11110000 A
b11110000 N
b11110000 ^
b11110000 #
b11110000 3
b11110000 Y
b11110000 b
b10001001 *
b10001001 D
b10001001 O
b10001001 a
b100001 V
b100 &
b100 =
b100 Z
1,
#530
0,
#535
06
18
b0 C
b0 T
0;
0<
1>
b1000000001000 W
1"
1X
b1 ]
b100010 V
0$
b0 )
b0 B
b0 Q
b0 R
1,
#540
0,
