Laboratorios/Lab03/TABLA2SOP/TABLA2SOP.v
module gates();
reg A, B, C; //declarar las 3 entradas
wire w1,w2,w3,w4,w5,w6,w7,w8,OUT; // 3 salidas para los Not, 3 salidas para los and y una para el or final
//orden de entradas y salidas de cada compuerta
not U1(w1,A);
not U2(w2,B);
not U3(w3,C);
and U4(w4,w1,w2,C);
and U5(w5,A,B,w3);
and U6(w6,A,B,C);
or  U7(OUT,w4,w5,w6);
initial begin
  $display("A B C | Y");
  $display("--------");
  $monitor("%b %b %b| %b", A, B, C, OUT);
  A = 0; B = 0; C = 0;
  #1  C = 1;
  #1  B = 1; C = 0;
  #1  C = 1;
  #1  A = 1; B = 0; C = 0;
  #1  C = 1;
  #1  B = 1; C = 0;
  #1  C = 1;
  #1 $finish;
end

initial
  begin
    $dumpfile("TABLA2SOP_tb.vcd");
    $dumpvars(0, gates);
  end

endmodule

Laboratorios/Lab03/TABLA2SOP/TABLA2SOP_tb.vcd
$date
	Sat Aug 01 17:26:44 2020
$end
$version
	Icarus Verilog
$end
$timescale
	1s
$end
$scope module gates $end
$var wire 1 ! OUT $end
$var wire 1 " w1 $end
$var wire 1 # w2 $end
$var wire 1 $ w3 $end
$var wire 1 % w4 $end
$var wire 1 & w5 $end
$var wire 1 ' w6 $end
$var reg 1 ( A $end
$var reg 1 ) B $end
$var reg 1 * C $end
$upscope $end
$enddefinitions $end
#0
$dumpvars
0*
0)
0(
0'
0&
0%
1$
1#
1"
0!
$end
#1
1!
1%
0$
1*
#2
0!
0%
1$
0#
0*
1)
#3
0$
1*
#4
1$
1#
0"
0*
0)
1(
#5
0$
1*
#6
1!
1&
1$
0#
0*
1)
#7
0&
1'
0$
1*
