Laboratorios/Lab06/ejercicio5y6.v
//flip flop D con reset asincrono y set sincrono
module FFD5 (input wire clock, reset, set, input wire [3:0]D, output reg [3:0]Q);
always @ (posedge clock, posedge reset, posedge set) begin
  if (reset) begin
    Q <= 4'b0;
    end
  else if (set) begin
    Q <= 4'b1111;
    end
  else
    Q <= D;
    end
endmodule

//flip flop D de 2 entradas, para ejercicio 1
module FD1 (input wire clock, reset, input wire D, output reg Q);
always @ (posedge clock or posedge reset) begin
  if (reset)begin
  Q <= 1'b0;
  end
  else begin
  Q <= D;
  end
  end
  endmodule

// modulo EJERCICIO 1
module FINALEJ1 (input wire A, B, clock, reset, output wire Y);
wire  S1F, S0F, S1, S0;
assign S1F = (S0 & B) | (S1 & A & B);
assign S0F = ~S1 & ~S0 & A;
assign Y = S1 & A & B;
FD1 E2(clock, reset, S1F, S1);
FD1 E3(clock, reset, S0F, S0);
endmodule

//modulo EJERCICIO 3
module FINALEJ3 (input wire P, clock, reset, output wire Y2,Y1,Y0);
wire  S2, S1, S0, S2F, S1F, S0F;
assign S2F = (~S2 & S1 & S0 & P) | (~S2 & ~S1 & ~S0 & ~P) | (S2 & ~S1 & S0) | (S2 & ~S0 & P) | (S2 & S1 & ~P);
assign S1F = (~S1 & S0 & P) |  (S1 & ~S0 & P) | (S1 & S0 & ~P) |  (~S1 & ~S0 & ~P);
assign S0F = ~S0;

FD1 E5(clock, reset, S2F, S2);
FD1 E6(clock, reset, S1F, S1);
FD1 E7(clock, reset, S0F, S0);

assign Y2 = S2;
assign Y1 = ~S2 & S1 | S2 & ~S1;
assign Y0 = ~S1 & S0 | ~S0 & S1;

endmodule

Laboratorios/Lab06/ejercicio5y6_tb.v
`include "ejercicio5y6.v"

module testbench();
wire [3:0]Q1;
reg [3:0]D1;
wire O0,O3,O2,O1;
reg A, B, p3;
reg clock, RST, ST;

FFD5      U1(clock, RST,ST, D1, Q1);
FINALEJ1  U3(p1, p2, clock, RST, O0);
FINALEJ3  U4(p3, clock, RST, O3, O2, O1);

always
  begin
  clock <=0;
  #1 clock <=~clock; #1 ;
  end
always
  begin
    ST <=0;
    #1 ST <=~ST; #1 ;
    end
//testbench flip flop d con reset asincrono
  initial begin
  $display(" Prueba ffrst");
  $display("S C R  D    |  Q ");
  $display("------------|-----");
  $monitor("%b %b %b %b  | %b  ", ST,clock, RST, D1[3:0], Q1[3:0]);
     RST = 1; D1[3] = 1; D1[2] = 1; D1[1] = 0; D1[0] = 0;
  #3 RST = 0; D1[3] = 0; D1[2] = 1; D1[1] = 1; D1[0] = 0;
  #3 RST = 0; D1[3] = 1; D1[2] = 1; D1[1] = 1; D1[0] = 1;
  #3 RST = 0; D1[3] = 0; D1[2] = 0; D1[1] = 1; D1[0] = 1;
  #3 RST = 0; D1[3] = 1; D1[2] = 1; D1[1] = 0; D1[0] = 1;
  end

  initial begin
  #13
  $display(" EJERCICIO 1 ");
  $display("clk A B | Y ");
  $display("--------|---");
  $monitor("%b  %b | %b " , A, B, O0);
  A = 0; B = 0;
#2	A = 0; B = 1;
#2	A = 1; B = 0;
#2	A = 1; B = 1;
#2	A = 0; B = 1;
#2	A = 0; B = 0;
#2	A = 0; B = 1;
#2	A = 1; B = 0;
#2	A = 1; B = 1;
#2	A = 0; B = 1;
  end

  initial begin
  #41
  $display(" EJERCICIO 3 ");
  $display("clk p |  Y ");
  $display("------|----");
  $monitor("%b  %b  | %b %b %b " ,clock,p3, O3,O2,O1);
     p3 = 1; RST = 1;
     p3 = 1; RST = 0;
     p3 = 1;
  #2 p3 = 1;
  #2 p3 = 1;
  #2 p3 = 1;
  #2 p3 = 1;
  #2 p3 = 1;
  #2 p3 = 1;
  #2 p3 = 1;
  #2 p3 = 0;
  #2 p3 = 0;
  #2 p3 = 0;
  #2 p3 = 0;
  #2 p3 = 0;
  #2 p3 = 0;
  #2 p3 = 0;
  #2 p3 = 0;
  end

  initial
    #73 $finish;
  initial begin
      $dumpfile("ejercicio5y6_tb.vcd");
      $dumpvars(0, testbench);
    end
  endmodule

Laboratorios/Lab06/ejercicio5y6_tb.vcd
$date
	Sat Sep 05 05:39:40 2020
$end
$version
	Icarus Verilog
$end
$timescale
	1s
$end
$scope module testbench $end
$var wire 1 ! p1 $end
$var wire 1 " p2 $end
$var wire 4 # Q1 [3:0] $end
$var wire 1 $ O3 $end
$var wire 1 % O2 $end
$var wire 1 & O1 $end
$var wire 1 ' O0 $end
$var reg 1 ( A $end
$var reg 1 ) B $end
$var reg 4 * D1 [3:0] $end
$var reg 1 + RST $end
$var reg 1 , ST $end
$var reg 1 - clock $end
$var reg 1 . p3 $end
$scope module U1 $end
$var wire 4 / D [3:0] $end
$var wire 1 - clock $end
$var wire 1 + reset $end
$var wire 1 , set $end
$var reg 4 0 Q [3:0] $end
$upscope $end
$scope module U3 $end
$var wire 1 ! A $end
$var wire 1 " B $end
$var wire 1 1 S0F $end
$var wire 1 2 S1F $end
$var wire 1 ' Y $end
$var wire 1 - clock $end
$var wire 1 + reset $end
$var wire 1 3 S1 $end
$var wire 1 4 S0 $end
$scope module E2 $end
$var wire 1 2 D $end
$var wire 1 - clock $end
$var wire 1 + reset $end
$var reg 1 3 Q $end
$upscope $end
$scope module E3 $end
$var wire 1 1 D $end
$var wire 1 - clock $end
$var wire 1 + reset $end
$var reg 1 4 Q $end
$upscope $end
$upscope $end
$scope module U4 $end
$var wire 1 . P $end
$var wire 1 5 S0F $end
$var wire 1 6 S1F $end
$var wire 1 7 S2F $end
$var wire 1 & Y0 $end
$var wire 1 % Y1 $end
$var wire 1 $ Y2 $end
$var wire 1 - clock $end
$var wire 1 + reset $end
$var wire 1 8 S2 $end
$var wire 1 9 S1 $end
$var wire 1 : S0 $end
$scope module E5 $end
$var wire 1 7 D $end
$var wire 1 - clock $end
$var wire 1 + reset $end
$var reg 1 8 Q $end
$upscope $end
$scope module E6 $end
$var wire 1 6 D $end
$var wire 1 - clock $end
$var wire 1 + reset $end
$var reg 1 9 Q $end
$upscope $end
$scope module E7 $end
$var wire 1 5 D $end
$var wire 1 - clock $end
$var wire 1 + reset $end
$var reg 1 : Q $end
$upscope $end
$upscope $end
$upscope $end
$enddefinitions $end
#0
$dumpvars
0:
09
08
x7
x6
15
04
03
02
x1
b0 0
b1100 /
x.
0-
0,
1+
b1100 *
x)
x(
0'
0&
0%
0$
b0 #
z"
z!
$end
#1
1,
1-
#2
0,
0-
#3
x2
x%
x&
05
b1111 #
b1111 0
x4
x$
x8
x9
1:
1,
1-
b110 *
b110 /
0+
#4
0,
0-
#5
x&
x'
15
0:
x3
1,
1-
#6
0,
0-
b1111 *
b1111 /
#7
05
1:
1,
1-
#8
0,
0-
#9
x&
15
0:
1,
1-
b11 *
b11 /
#10
0,
0-
#11
05
1:
1,
1-
#12
0,
0-
b1101 *
b1101 /
#13
x&
15
0:
1,
1-
0)
0(
#14
0,
0-
#15
05
1:
1,
1-
1)
#16
0,
0-
#17
x&
15
0:
1,
1-
0)
1(
#18
0,
0-
#19
05
1:
1,
1-
1)
#20
0,
0-
#21
x&
15
0:
1,
1-
0(
#22
0,
0-
#23
05
1:
1,
1-
0)
#24
0,
0-
#25
x&
15
0:
1,
1-
1)
#26
0,
0-
#27
05
1:
1,
1-
0)
1(
#28
0,
0-
#29
x&
15
0:
1,
1-
1)
#30
0,
0-
#31
05
1:
1,
1-
0(
#32
0,
0-
#33
x&
15
0:
1,
1-
#34
0,
0-
#35
05
1:
1,
1-
#36
0,
0-
#37
x&
15
0:
1,
1-
#38
0,
0-
#39
05
1:
1,
1-
#40
0,
0-
#41
x6
x&
15
b1111 #
b1111 0
0:
1,
1-
0+
1.
#42
0,
0-
#43
05
1:
1,
1-
#44
0,
0-
#45
x6
x&
15
0:
1,
1-
#46
0,
0-
#47
05
1:
1,
1-
#48
0,
0-
#49
x6
x&
15
0:
1,
1-
#50
0,
0-
#51
05
1:
1,
1-
#52
0,
0-
#53
x6
x&
15
0:
1,
1-
#54
0,
0-
#55
05
1:
1,
1-
#56
0,
0-
#57
x&
15
0:
1,
1-
0.
#58
0,
0-
#59
05
1:
1,
1-
#60
0,
0-
#61
x&
15
0:
1,
1-
#62
0,
0-
#63
05
1:
1,
1-
#64
0,
0-
#65
x&
15
0:
1,
1-
#66
0,
0-
#67
05
1:
1,
1-
#68
0,
0-
#69
x&
15
0:
1,
1-
#70
0,
0-
#71
05
1:
1,
1-
#72
0,
0-
#73
x&
15
0:
1,
1-
