Laboratorios/Lab06/ejercicio5y6.v
//flip flop D con reset asincrono y set sincrono
module FFD5 (input wire clock, reset, set, input wire [3:0]D, output reg [3:0]Q);
always @ (posedge clock, posedge reset, posedge set) begin
  if (reset) begin
    Q <= 4'b0;
    end
  else if (set) begin
    Q <= 4'b1111;
    end
  else
    Q <= D;
    end
endmodule

//flip flop D de 2 entradas, para ejercicio 1
module FD1 (input wire clock, reset, input wire D, output reg Q);
always @ (posedge clock or posedge reset) begin
  if (reset)begin
  Q <= 1'b0;
  end
  else begin
  Q <= D;
  end
  end
  endmodule

// modulo EJERCICIO 1
module FINALEJ1 (input wire A, B, clock, reset, output wire Y);
wire  S1F, S0F, S1, S0;
assign S1F = (S0 & B) | (S1 & A & B);
assign S0F = ~S1 & ~S0 & A;
assign Y = S1 & A & B;
FD1 E2(clock, reset, S1F, S1);
FD1 E3(clock, reset, S0F, S0);
endmodule

//modulo EJERCICIO 3
module FINALEJ3 (input wire P, clock, reset, output wire Y2,Y1,Y0);
wire  S2, S1, S0, S2F, S1F, S0F;
assign S2F = (~S2 & S1 & S0 & P) | (~S2 & ~S1 & ~S0 & ~P) | (S2 & ~S1 & S0) | (S2 & ~S0 & P) | (S2 & S1 & ~P);
assign S1F = (~S1 & S0 & P) |  (S1 & ~S0 & P) | (S1 & S0 & ~P) |  (~S1 & ~S0 & ~P);
assign S0F = ~S0;

FD1 E5(clock, reset, S2F, S2);
FD1 E6(clock, reset, S1F, S1);
FD1 E7(clock, reset, S0F, S0);

assign Y2 = S2;
assign Y1 = ~S2 & S1 | S2 & ~S1;
assign Y0 = ~S1 & S0 | ~S0 & S1;

endmodule

Laboratorios/Lab06/ejercicio5y6_tb.v
`include "ejercicio5y6.v"

module testbench();
wire [3:0]Q1;
reg [3:0]D1;
wire O0,O3,O2,O1;
reg A, B, p3;
reg clock, RST, ST;

FFD5      U1(clock, RST,ST, D1, Q1);
FINALEJ1  U3(A, B, clock, RST, O0);
FINALEJ3  U4(p3, clock, RST, O3, O2, O1);

always
  #5 clock <=~clock;

  always
    #1 ST <=~ST;
//testbench flip flop d con reset asincrono
  initial begin
  $display(" Prueba ffrst");
  $display("S C R  D    |  Q ");
  $display("------------|-----");
  $monitor("%b %b %b %b  | %b  ", ST,clock, RST, D1[3:0], Q1[3:0]);
     RST = 1; D1[3] = 1; D1[2] = 1; D1[1] = 0; D1[0] = 0; clock = 0;
  #3 RST = 0; D1[3] = 0; D1[2] = 1; D1[1] = 1; D1[0] = 0;
  #3 RST = 0; D1[3] = 1; D1[2] = 1; D1[1] = 1; D1[0] = 1;
  #3 RST = 0; D1[3] = 0; D1[2] = 0; D1[1] = 1; D1[0] = 1;
  #3 RST = 0; D1[3] = 1; D1[2] = 1; D1[1] = 0; D1[0] = 1;
  end

  initial begin
  #13
  $display(" EJERCICIO 1 ");
  $display("clk A B | Y ");
  $display("--------|---");
  $monitor("%b  %b %b | %b  " ,clock, A, B, O0);
  end
  initial begin
    A = 0; B = 0; RST = 0; clock = 0;
    #1	RST = 1;
    #1	RST = 0;
    #10
    A = 1; B = 0;
    #20
    A = 0; B = 0;
    #10
    A = 1; B = 1;
  end

  initial begin
  #56
  $display(" EJERCICIO 3 ");
  $display("clk p |  Y ");
  $display("------|----");
  $monitor("%b  %b  | %b %b %b " ,clock,p3, O3,O2,O1);
  end
  initial begin
  #57
     p3 = 1; RST = 1; 
  #1 p3 = 1; RST = 0;
  #1 p3 = 1;
  #1 p3 = 1;
  #1 p3 = 1;
  #1 p3 = 1;
  #1 p3 = 1;
  #1 p3 = 1;
  #1 p3 = 1;
  #1 p3 = 1;
  #1 p3 = 0;
  #1 p3 = 0;
  #1 p3 = 0;
  #1 p3 = 0;
  #1 p3 = 0;
  #1 p3 = 0;
  #1 p3 = 0;
  #1 p3 = 0;
  end

  initial
    #100 $finish;
  initial begin
      $dumpfile("ejercicio5y6_tb.vcd");
      $dumpvars(0, testbench);
    end
  endmodule

Laboratorios/Lab06/ejercicio5y6_tb.vcd
$date
	Sat Sep 05 12:38:16 2020
$end
$version
	Icarus Verilog
$end
$timescale
	1s
$end
$scope module testbench $end
$var wire 4 ! Q1 [3:0] $end
$var wire 1 " O3 $end
$var wire 1 # O2 $end
$var wire 1 $ O1 $end
$var wire 1 % O0 $end
$var reg 1 & A $end
$var reg 1 ' B $end
$var reg 4 ( D1 [3:0] $end
$var reg 1 ) RST $end
$var reg 1 * ST $end
$var reg 1 + clock $end
$var reg 1 , p3 $end
$scope module U1 $end
$var wire 4 - D [3:0] $end
$var wire 1 + clock $end
$var wire 1 ) reset $end
$var wire 1 * set $end
$var reg 4 . Q [3:0] $end
$upscope $end
$scope module U3 $end
$var wire 1 & A $end
$var wire 1 ' B $end
$var wire 1 / S0F $end
$var wire 1 0 S1F $end
$var wire 1 % Y $end
$var wire 1 + clock $end
$var wire 1 ) reset $end
$var wire 1 1 S1 $end
$var wire 1 2 S0 $end
$scope module E2 $end
$var wire 1 0 D $end
$var wire 1 + clock $end
$var wire 1 ) reset $end
$var reg 1 1 Q $end
$upscope $end
$scope module E3 $end
$var wire 1 / D $end
$var wire 1 + clock $end
$var wire 1 ) reset $end
$var reg 1 2 Q $end
$upscope $end
$upscope $end
$scope module U4 $end
$var wire 1 , P $end
$var wire 1 3 S0F $end
$var wire 1 4 S1F $end
$var wire 1 5 S2F $end
$var wire 1 $ Y0 $end
$var wire 1 # Y1 $end
$var wire 1 " Y2 $end
$var wire 1 + clock $end
$var wire 1 ) reset $end
$var wire 1 6 S2 $end
$var wire 1 7 S1 $end
$var wire 1 8 S0 $end
$scope module E5 $end
$var wire 1 5 D $end
$var wire 1 + clock $end
$var wire 1 ) reset $end
$var reg 1 6 Q $end
$upscope $end
$scope module E6 $end
$var wire 1 4 D $end
$var wire 1 + clock $end
$var wire 1 ) reset $end
$var reg 1 7 Q $end
$upscope $end
$scope module E7 $end
$var wire 1 3 D $end
$var wire 1 + clock $end
$var wire 1 ) reset $end
$var reg 1 8 Q $end
$upscope $end
$upscope $end
$upscope $end
$enddefinitions $end
#0
$dumpvars
x8
x7
x6
x5
x4
x3
02
01
00
0/
b1100 .
b1100 -
x,
0+
x*
0)
b1100 (
0'
0&
0%
x$
x#
x"
b1100 !
$end
#1
0$
0#
13
b0 !
b0 .
08
07
0"
06
1)
#2
0)
#3
b110 (
b110 -
#5
x#
x$
03
b110 !
b110 .
x"
x6
x7
18
1+
#6
b1111 (
b1111 -
#9
b11 (
b11 -
#10
0+
#12
1/
b1101 (
b1101 -
1&
#15
0/
x$
13
b1101 !
b1101 .
08
12
1+
#20
0+
#25
1/
03
02
18
1+
#30
0+
#32
0/
0&
#35
x$
13
08
1+
#40
0+
#42
1/
1'
1&
#45
0/
10
03
12
18
1+
#50
0+
#55
x$
1%
13
08
02
11
1+
#57
04
05
1/
00
0%
0$
0#
b0 !
b0 .
01
0"
06
07
1)
1,
#58
0)
#60
0+
#65
14
0/
1$
10
03
b1101 !
b1101 .
18
12
1+
#67
04
0,
#70
0+
#75
15
14
1%
10
0$
13
11
02
08
1+
#80
0+
#85
0$
0#
03
18
17
1"
16
1+
#90
0+
#95
04
1$
13
08
1+
