Laboratorios/Lab06/ejercicio5y6.v
//flip flop D con reset asincrono y set sincrono
module FFD5 (input wire clock, reset, set, input wire [3:0]D, output reg [3:0]Q);
always @ (posedge clock, posedge reset, posedge set) begin
  if (reset) begin
    Q <= 4'b0;
    end
  else if (set) begin
    Q <= 4'b1111;
    end
  else
    Q <= D;
    end
endmodule

//flip flop D de 2 entradas, para ejercicio 1
module FD1 (input wire clock, reset, input wire D, output reg Q);
always @ (posedge clock or posedge reset) begin
  if (reset)begin
  Q <= 1'b0;
  end
  else begin
  Q <= D;
  end
  end
  endmodule

// modulo EJERCICIO 1
module FINALEJ1 (input wire A, B, clock, reset, output wire Y);
wire  S1F, S0F, S1, S0;
assign S1F = (S0 & B) | (S1 & A & B);
assign S0F = ~S1 & ~S0 & A;
assign Y = S1 & A & B;
FD1 E2(clock, reset, S1F, S1);
FD1 E3(clock, reset, S0F, S0);
endmodule

//modulo EJERCICIO 3
module FINALEJ3 (input wire P, clock, reset, output wire Y2,Y1,Y0);
wire  S2, S1, S0, S2F, S1F, S0F;
assign S2F = (~S2 & S1 & S0 & P) | (~S2 & ~S1 & ~S0 & ~P) | (S2 & ~S1 & S0) | (S2 & ~S0 & P) | (S2 & S1 & ~P);
assign S1F = (~S1 & S0 & P) |  (S1 & ~S0 & P) | (S1 & S0 & ~P) |  (~S1 & ~S0 & ~P);
assign S0F = ~S0;

FD1 E5(clock, reset, S2F, S2);
FD1 E6(clock, reset, S1F, S1);
FD1 E7(clock, reset, S0F, S0);

assign Y2 = S2;
assign Y1 = ~S2 & S1 | S2 & ~S1;
assign Y0 = ~S1 & S0 | ~S0 & S1;

endmodule

Laboratorios/Lab06/ejercicio5y6_tb.v
`include "ejercicio5y6.v"

module testbench();
wire O0;
reg A, B;
reg clock, RST;

FINALEJ1  U1(A, B, clock, RST, O0);

always
  #1 clock <=~clock;

  initial begin
  $display(" EJERCICIO 1 ");
  $display("clk A B | Y ");
  $display("--------|---");
  $monitor("%b  %b %b | %b  " ,clock, A, B, O0);
  end
  initial begin
    A = 0; B = 0; RST = 0; clock = 0;
    #1	RST = 1;
    #1	RST = 0;
    #5
    A = 1; B = 0;
    #5
    A = 0; B = 0;
    #5
    A = 1; B = 1;
  end

  initial
    #20 $finish;
  initial begin
      $dumpfile("ejercicio5y6_tb.vcd");
      $dumpvars(0, testbench);
    end
  endmodule

Laboratorios/Lab06/ejercicio5y6_tb.vcd
$date
	Sat Sep 05 18:35:14 2020
$end
$version
	Icarus Verilog
$end
$timescale
	1s
$end
$scope module testbench $end
$var wire 1 ! O0 $end
$var reg 1 " A $end
$var reg 1 # B $end
$var reg 1 $ RST $end
$var reg 1 % clock $end
$scope module U1 $end
$var wire 1 " A $end
$var wire 1 # B $end
$var wire 1 & S0F $end
$var wire 1 ' S1F $end
$var wire 1 ! Y $end
$var wire 1 % clock $end
$var wire 1 $ reset $end
$var wire 1 ( S1 $end
$var wire 1 ) S0 $end
$scope module E2 $end
$var wire 1 ' D $end
$var wire 1 % clock $end
$var wire 1 $ reset $end
$var reg 1 ( Q $end
$upscope $end
$scope module E3 $end
$var wire 1 & D $end
$var wire 1 % clock $end
$var wire 1 $ reset $end
$var reg 1 ) Q $end
$upscope $end
$upscope $end
$upscope $end
$enddefinitions $end
#0
$dumpvars
x)
x(
0'
0&
0%
0$
0#
0"
0!
$end
#1
0(
0)
1%
1$
#2
0%
0$
#3
1%
#4
0%
#5
1%
#6
0%
#7
1)
1%
0&
1"
#8
0%
#9
1&
0)
1%
#10
0%
#11
0&
1)
1%
#12
0%
0"
#13
0)
1%
#14
0%
#15
1%
#16
0%
#17
1'
1)
1%
0&
1#
1"
#18
0%
#19
1!
1'
1(
0)
1%
