Laboratorios/Lab03/TABLA1SOP/TABLA1SOP.v
module gates();
reg A, B, C; //declarar las 3 entradas
wire w1,w2,w3,w4,w5,w6,w7,w8,OUT; // 3 salidas para los Not, 5 salidas para los and y una para el or final
//orden de entradas y salidas de cada compuerta
not U1(w1,A);
not U2(w2,B);
not U3(w3,C);
and U4(w4,w1,w2,w3);
and U5(w5,w1,B,w3);
and U6(w6,A,w2,w3);
and U7(w7,A,w2,C);
and U8(w8,A,B,C);
or  U9(OUT,w4,w5,w6,w7,w8);
initial begin
  $display("A B C | Y");
  $display("--------");
  $monitor("%b %b %b| %b", A, B, C, OUT);
  A = 0; B = 0; C = 0;
  #1  C = 1;
  #1  B = 1; C = 0;
  #1  C = 1;
  #1  A = 1; B = 0; C = 0;
  #1  C = 1;
  #1  B = 1; C = 0;
  #1  C = 1;
  #1 $finish;
end

initial
  begin
    $dumpfile("TABLA1SOP_tb.vcd");
    $dumpvars(0, gates);
  end

endmodule

Laboratorios/Lab03/TABLA1SOP/TABLA1SOP_tb.vcd
$date
	Sat Aug 01 17:13:51 2020
$end
$version
	Icarus Verilog
$end
$timescale
	1s
$end
$scope module gates $end
$var wire 1 ! OUT $end
$var wire 1 " w1 $end
$var wire 1 # w2 $end
$var wire 1 $ w3 $end
$var wire 1 % w4 $end
$var wire 1 & w5 $end
$var wire 1 ' w6 $end
$var wire 1 ( w7 $end
$var wire 1 ) w8 $end
$var reg 1 * A $end
$var reg 1 + B $end
$var reg 1 , C $end
$upscope $end
$enddefinitions $end
#0
$dumpvars
0,
0+
0*
0)
0(
0'
0&
1%
1$
1#
1"
1!
$end
#1
0!
0%
0$
1,
#2
1!
1&
1$
0#
0,
1+
#3
0!
0&
0$
1,
#4
1!
1'
1$
1#
0"
0,
0+
1*
#5
0'
1(
0$
1,
#6
0!
0(
1$
0#
0,
1+
#7
1!
1)
0$
1,
