Laboratorios/Lab09/Ejercicio 1/Lab09.v
//ejercicio 1
//flip flop D de 1 bit
module FD1 (input wire clock, reset, en, input wire D, output reg Q);
  always @ (posedge clock or posedge reset or en) begin
    if (reset)begin
    Q <= 1'b0;
    end
    else if (en) begin
    Q <= D;
    end
    end
  endmodule
//flip flop D de 2 bit
module FD2 (input wire clock, reset, en, input wire [1:0]D, output wire[1:0]Q);
  FD1 N1(clock, reset, en, D[0], Q[0]);
  FD1 N2(clock, reset, en, D[1], Q[1]);
  endmodule
//flip flop D de 4 bits
module FD4 (input wire clock, reset, en, input wire [3:0]D, output wire[3:0]Q);
  FD1 N1(clock, reset, en, D[0], Q[0]);
  FD1 N2(clock, reset, en, D[1], Q[1]);
  FD1 N3(clock, reset, en, D[2], Q[2]);
  FD1 N4(clock, reset, en, D[3], Q[3]);
  endmodule
//flip flip 'timescale
module FFT (input wire clock, reset, en, output wire Q);
  wire NOTQ;
  assign NOTQ = ~Q;
  FD1 N5(clock, reset, en, NOTQ, Q);
  endmodule
//flip flop JK
module FFJK (input wire J, K, clock, reset, en, output wire Q);
  wire D, AND1, AND2, NOTQ, NOTK;
  not U1(NOTQ,Q);
  not U2(NOTK,K);
  and U3(AND1,NOTK, Q);
  and U4(AND2, J, NOTQ);
  or  U5(D,AND1, AND2);
  FD1 N7(clock, reset, en, D, Q);
  endmodule
//buffer triestado de 4 bits
module buffer (input wire [3:0]in, input wire enable, output wire [3:0]out);
  assign out = enable? in: 4'bz;
  endmodule
//modulo del microcode implementado con cases
module microcode (input wire [6:0]INPUT, output reg [12:0]OUTPUT);
  always @ (*)begin
  case(INPUT)
  7'bxxxxxx0: //0
  OUTPUT <= 13'b1000000001000;
  7'b00001x1://1
  OUTPUT <= 13'b0100000001000;
  7'b00000x1://2
  OUTPUT <= 13'b1000000001000;
  7'b00011x1://3
  OUTPUT <= 13'b1000000001000;
  7'b00010x1://4
  OUTPUT <= 13'b0100000001000;
  7'b0010xx1://5
  OUTPUT <= 13'b0001001000010;
  7'b0011xx1://6
  OUTPUT <= 13'b1001001100000;
  7'b0100xx1://7
  OUTPUT <= 13'b0011010000010;
  7'b0101xx1://8
  OUTPUT <= 13'b0011010000100;
  7'b0110xx1://9
  OUTPUT <= 13'b1011010100000;
  7'b0111xx1: //10
  OUTPUT <= 13'b1000000111000;
  7'b1000x11: //11
  OUTPUT <= 13'b0100000001000;
  7'b1000x01: //12
  OUTPUT <= 13'b1000000001000;
  7'b1001x11: //13
  OUTPUT <= 13'b1000000001000;
  7'b1001x01: //14
  OUTPUT <= 13'b0100000001000;
  7'b1010xx1: //15
  OUTPUT <= 13'b0011011000010;
  7'b1011xx1: //16
  OUTPUT <= 13'b1011011100000;
  7'b1100xx1: //17
  OUTPUT <= 13'b0100000001000;
  7'b1101xx1: //18
  OUTPUT <= 13'b0000000001001;
  7'b1110xx1: //19
  OUTPUT <= 13'b0011100000010;
  7'b1111xx1: //20
  OUTPUT <= 13'b1011100100000;
  default:
    OUTPUT <= 13'b0;
  endcase
  end
  endmodule

Laboratorios/Lab09/Ejercicio 5/Ejercicio5_tb.v
`include "Lab09.v"
module testbench();
reg clock, reset,EN, D, J, K, enable;
reg [1:0]D1;
reg [3:0]D2;
reg [3:0]in;
reg [6:0]INPUT;
wire [1:0]Q1;
wire [3:0]Q2;
wire [3:0]OUT;
wire [12:0]OUTPUT;
wire Q, QT, QJK;
microcode E7(INPUT, OUTPUT);
  initial begin
  #1
  $display(" MICROCODE  ");
  $display("INPUT | OUTPUT ");
  $display("---------|----");
  $monitor("%b | %b " ,INPUT, OUTPUT);
      INPUT = 7'bxxxxxx0;
  #3 INPUT = 7'b00001x1;
  #3 INPUT = 7'b00000x1;
  #3 INPUT = 7'b00011x1;
  #3 INPUT = 7'b00010x1;
  #3 INPUT = 7'b0010xx1;
  #3 INPUT = 7'b0011xx1;
  #3 INPUT = 7'b0100xx1;
  #3 INPUT = 7'b0101xx1;
  #3 INPUT = 7'b0110xx1;
  #3 INPUT = 7'b0111xx1;
  #3 INPUT = 7'b1000x11;
  #3 INPUT = 7'b1000x01;
  #3 INPUT = 7'b1001x11;
  #3 INPUT = 7'b1001x01;
  #3 INPUT = 7'b1010xx1;
  #3 INPUT = 7'b1011xx1;
  #3 INPUT = 7'b1100xx1;
  #3 INPUT = 7'b1101xx1;
  #3 INPUT = 7'b1110xx1;
  #3 INPUT = 7'b1111xx1;

  #3 INPUT = 7'b1111111;
  #3 INPUT = 7'b1111001;
  #3 INPUT = 7'b1111011;
  #3 INPUT = 7'b1111101;
  #3 INPUT = 7'b1110001;
  #3 INPUT = 7'b1101011;
  #3 INPUT = 7'b1000001;
  #3 INPUT = 7'b1101011;
  #3 INPUT = 7'b1111101;
  #3 INPUT = 7'b1000001;

  end
  initial
    #94 $finish;
  initial begin
      $dumpfile("Ejercicio5_tb.vcd");
      $dumpvars(0, testbench);
    end
  endmodule

Laboratorios/Lab09/Ejercicio 5/contador.vcd
$date
	Sat Oct 31 00:34:29 2020
$end
$version
	Icarus Verilog
$end
$timescale
	1s
$end
$scope module testbench $end
$var wire 13 ! OUTPUT [12:0] $end
$var reg 7 " INPUT [6:0] $end
$scope module E7 $end
$var wire 7 # INPUT [6:0] $end
$var reg 13 $ OUTPUT [12:0] $end
$upscope $end
$upscope $end
$enddefinitions $end
#0
$dumpvars
bx $
bx #
bx "
bx !
$end
#1
b1000000001000 !
b1000000001000 $
bx0 "
bx0 #
#4
b100000001000 !
b100000001000 $
b1x1 "
b1x1 #
#7
b1000000001000 !
b1000000001000 $
b0x1 "
b0x1 #
#10
b11x1 "
b11x1 #
#13
b100000001000 !
b100000001000 $
b10x1 "
b10x1 #
#16
b1001000010 !
b1001000010 $
b10xx1 "
b10xx1 #
#19
b1001001100000 !
b1001001100000 $
b11xx1 "
b11xx1 #
#22
b11010000010 !
b11010000010 $
b100xx1 "
b100xx1 #
#25
b11010000100 !
b11010000100 $
b101xx1 "
b101xx1 #
#28
b1011010100000 !
b1011010100000 $
b110xx1 "
b110xx1 #
#31
b1000000111000 !
b1000000111000 $
b111xx1 "
b111xx1 #
#34
b100000001000 !
b100000001000 $
b1000x11 "
b1000x11 #
#37
b1000000001000 !
b1000000001000 $
b1000x01 "
b1000x01 #
#40
b1001x11 "
b1001x11 #
#43
b100000001000 !
b100000001000 $
b1001x01 "
b1001x01 #
#46
b11011000010 !
b11011000010 $
b1010xx1 "
b1010xx1 #
#49
b1011011100000 !
b1011011100000 $
b1011xx1 "
b1011xx1 #
#52
b100000001000 !
b100000001000 $
b1100xx1 "
b1100xx1 #
#55
b1001 !
b1001 $
b1101xx1 "
b1101xx1 #
#58
b11100000010 !
b11100000010 $
b1110xx1 "
b1110xx1 #
#61
b1011100100000 !
b1011100100000 $
b1111xx1 "
b1111xx1 #
#64
b1111111 "
b1111111 #
#67
b1111001 "
b1111001 #
#70
b1111011 "
b1111011 #
#73
b1111101 "
b1111101 #
#76
b11100000010 !
b11100000010 $
b1110001 "
b1110001 #
#79
b1001 !
b1001 $
b1101011 "
b1101011 #
#82
b1000000001000 !
b1000000001000 $
b1000001 "
b1000001 #
#85
b1001 !
b1001 $
b1101011 "
b1101011 #
#88
b1011100100000 !
b1011100100000 $
b1111101 "
b1111101 #
#91
b1000000001000 !
b1000000001000 $
b1000001 "
b1000001 #
