Laboratorios/Lab09/Ejercicio 1/Lab09.v
//ejercicio 1
//flip flop D de 1 bit
module FD1 (input wire clock, reset, en, input wire D, output reg Q);
  always @ (posedge clock or posedge reset or en) begin
    if (reset)begin
    Q <= 1'b0;
    end
    else if (en) begin
    Q <= D;
    end
    end
  endmodule
//flip flop D de 2 bit
module FD2 (input wire clock, reset, en, input wire [1:0]D, output wire[1:0]Q);
  FD1 N1(clock, reset, en, D[0], Q[0]);
  FD1 N2(clock, reset, en, D[1], Q[1]);
  endmodule
//flip flop D de 4 bits
module FD4 (input wire clock, reset, en, input wire [3:0]D, output wire[3:0]Q);
  FD1 N1(clock, reset, en, D[0], Q[0]);
  FD1 N2(clock, reset, en, D[1], Q[1]);
  FD1 N3(clock, reset, en, D[2], Q[2]);
  FD1 N4(clock, reset, en, D[3], Q[3]);
  endmodule
//flip flip 'timescale
module FFT (input wire clock, reset, en, output wire Q);
  wire NOTQ;
  assign NOTQ = ~Q;
  FD1 N5(clock, reset, en, NOTQ, Q);
  endmodule
//flip flop JK
module FFJK (input wire J, K, clock, reset, en, output wire Q);
  wire D, AND1, AND2, NOTQ, NOTK;
  not U1(NOTQ,Q);
  not U2(NOTK,K);
  and U3(AND1,NOTK, Q);
  and U4(AND2, J, NOTQ);
  or  U5(D,AND1, AND2);
  FD1 N7(clock, reset, en, D, Q);
  endmodule
//buffer triestado de 4 bits
module buffer (input wire [3:0]in, input wire enable, output wire [3:0]out);
  assign out = enable? in: 4'bz;
  endmodule
//modulo del microcode implementado con cases
module microcode (input wire [6:0]INPUT, output reg [12:0]OUTPUT);
  always @ (*)begin
  case(INPUT)
  7'bxxxxxx0: //0
  OUTPUT <= 13'b1000000001000;
  7'b00001x1://1
  OUTPUT <= 13'b0100000001000;
  7'b00000x1://2
  OUTPUT <= 13'b1000000001000;
  7'b00011x1://3
  OUTPUT <= 13'b1000000001000;
  7'b00010x1://4
  OUTPUT <= 13'b0100000001000;
  7'b0010xx1://5
  OUTPUT <= 13'b0001001000010;
  7'b0011xx1://6
  OUTPUT <= 13'b1001001100000;
  7'b0100xx1://7
  OUTPUT <= 13'b0011010000010;
  7'b0101xx1://8
  OUTPUT <= 13'b0011010000100;
  7'b0110xx1://9
  OUTPUT <= 13'b1011010100000;
  7'b0111xx1: //10
  OUTPUT <= 13'b1000000111000;
  7'b1000x11: //11
  OUTPUT <= 13'b0100000001000;
  7'b1000x01: //12
  OUTPUT <= 13'b1000000001000;
  7'b1001x11: //13
  OUTPUT <= 13'b1000000001000;
  7'b1001x01: //14
  OUTPUT <= 13'b0100000001000;
  7'b1010xx1: //15
  OUTPUT <= 13'b0011011000010;
  7'b1011xx1: //16
  OUTPUT <= 13'b1011011100000;
  7'b1100xx1: //17
  OUTPUT <= 13'b0100000001000;
  7'b1101xx1: //18
  OUTPUT <= 13'b0000000001001;
  7'b1110xx1: //19
  OUTPUT <= 13'b0011100000010;
  7'b1111xx1: //20
  OUTPUT <= 13'b1011100100000;
  default:
    OUTPUT <= 13'b0;
  endcase
  end
  endmodule

Laboratorios/Lab09/Ejercicio 1/ejercicio1_tb.v
`include "Lab09.v"
module testbench();
reg clock, reset,EN, D, J, K, enable;
reg [1:0]D1;
reg [3:0]D2;
reg [3:0]in;
reg [6:0]INPUT;
wire [1:0]Q1;
wire [3:0]Q2;
wire [3:0]OUT;
wire [12:0]OUTPUT;
wire Q, QT, QJK;
FD1 E1(clock, reset, EN, D, Q);
FD2 E2(clock, reset, EN, D1, Q1);
FD4 E3(clock, reset, EN, D2, Q2);
always
  #1 clock <=~clock;

  initial begin
  clock = 0;
  #1
  $display(" FLIP FLOP D 1 BIT  ");
  $display("clk en D | Q ");
  $display("---------|----");
  $monitor("%b %b %b | %b " ,clock,EN,D, Q);
    reset = 0;EN = 0; D = 0;
  #1 reset = 1;
  #1 reset = 0;
  #3 EN = 1; D = 1;
  #3 EN = 1; D = 1;
  #3 EN = 0; D = 0;
  #3 EN = 0; D = 0;
  end
  initial begin
  #16
  $display(" FLIP FLOP D 2 BIT  ");
  $display("clk en D | Q ");
  $display("---------|----");
  $monitor("%b %b %b | %b " ,clock,EN,D1, Q1);
    reset = 0; EN = 0; D1 = 2'b0;
  #1 reset = 1;
  #1 reset = 0;
  #3 EN = 1; D1 = 2'b01;
  #3 EN = 1; D1 = 2'b01;
  #3 EN = 0; D1 = 2'b0;
  #3 EN = 0; D1 = 2'b0;
  end
  initial begin
  #41
  $display(" FLIP FLOP D 4 BIT  ");
  $display("clk en D | Q ");
  $display("---------|----");
  $monitor("%b %b %b | %b " ,clock,EN,D2, Q2);
    reset = 0; EN = 0; D2 = 4'b0;
  #1 reset = 1;
  #1 reset = 0;
  #3 EN = 1; D2 = 4'b0101;
  #3 EN = 1; D2 = 4'b0101;
  #3 EN = 0; D2 = 4'b0;
  #3 EN = 0; D2 = 4'b0;
  end
  initial
    #56 $finish;
  initial begin
      $dumpfile("ejercicio1_tb.vcd");
      $dumpvars(0, testbench);
    end
  endmodule

Laboratorios/Lab09/Ejercicio 1/ejercicio1_tb.vcd
$date
	Fri Oct 30 23:58:50 2020
$end
$version
	Icarus Verilog
$end
$timescale
	1s
$end
$scope module testbench $end
$var wire 4 ! Q2 [3:0] $end
$var wire 2 " Q1 [1:0] $end
$var wire 1 # Q $end
$var reg 1 $ D $end
$var reg 2 % D1 [1:0] $end
$var reg 4 & D2 [3:0] $end
$var reg 1 ' EN $end
$var reg 1 ( clock $end
$var reg 1 ) reset $end
$scope module E1 $end
$var wire 1 $ D $end
$var wire 1 ( clock $end
$var wire 1 ' en $end
$var wire 1 ) reset $end
$var reg 1 # Q $end
$upscope $end
$scope module E2 $end
$var wire 2 * D [1:0] $end
$var wire 1 ( clock $end
$var wire 1 ' en $end
$var wire 1 ) reset $end
$var wire 2 + Q [1:0] $end
$scope module N1 $end
$var wire 1 , D $end
$var wire 1 ( clock $end
$var wire 1 ' en $end
$var wire 1 ) reset $end
$var reg 1 - Q $end
$upscope $end
$scope module N2 $end
$var wire 1 . D $end
$var wire 1 ( clock $end
$var wire 1 ' en $end
$var wire 1 ) reset $end
$var reg 1 / Q $end
$upscope $end
$upscope $end
$scope module E3 $end
$var wire 4 0 D [3:0] $end
$var wire 1 ( clock $end
$var wire 1 ' en $end
$var wire 1 ) reset $end
$var wire 4 1 Q [3:0] $end
$scope module N1 $end
$var wire 1 2 D $end
$var wire 1 ( clock $end
$var wire 1 ' en $end
$var wire 1 ) reset $end
$var reg 1 3 Q $end
$upscope $end
$scope module N2 $end
$var wire 1 4 D $end
$var wire 1 ( clock $end
$var wire 1 ' en $end
$var wire 1 ) reset $end
$var reg 1 5 Q $end
$upscope $end
$scope module N3 $end
$var wire 1 6 D $end
$var wire 1 ( clock $end
$var wire 1 ' en $end
$var wire 1 ) reset $end
$var reg 1 7 Q $end
$upscope $end
$scope module N4 $end
$var wire 1 8 D $end
$var wire 1 ( clock $end
$var wire 1 ' en $end
$var wire 1 ) reset $end
$var reg 1 9 Q $end
$upscope $end
$upscope $end
$upscope $end
$enddefinitions $end
#0
$dumpvars
x9
x8
x7
x6
x5
x4
x3
x2
bx 1
bx 0
x/
x.
x-
x,
bx +
bx *
x)
0(
x'
bx &
bx %
x$
x#
bx "
bx !
$end
#1
1(
0$
0'
0)
#2
0#
0-
b0 "
b0 +
0/
03
05
07
b0 !
b0 1
09
0(
1)
#3
1(
0)
#4
0(
#5
1(
#6
x9
x7
x5
bx !
bx 1
x3
x/
bx "
bx +
x-
1#
0(
1$
1'
#7
1(
#8
0(
#9
1(
#10
0(
#11
1(
#12
0(
0$
0'
#13
1(
#14
0(
#15
1(
#16
0(
0,
0.
b0 %
b0 *
#17
0#
0-
b0 "
b0 +
0/
03
05
07
b0 !
b0 1
09
1(
1)
#18
0(
0)
#19
1(
#20
0(
#21
b1 "
b1 +
1-
x9
x7
x5
bx !
bx 1
x3
1(
1,
b1 %
b1 *
1'
#22
0(
#23
1(
#24
0(
#25
1(
#26
0(
#27
1(
0,
b0 %
b0 *
0'
#28
0(
#29
1(
#30
0(
#31
1(
#32
0(
#33
1(
#34
0(
#35
1(
#36
0(
#37
1(
#38
0(
#39
1(
#40
0(
#41
1(
02
04
06
08
b0 &
b0 0
#42
b0 "
b0 +
0-
03
05
07
b0 !
b0 1
09
0(
1)
#43
1(
0)
#44
0(
#45
1(
#46
0(
12
16
b101 &
b101 0
1'
#47
13
b101 !
b101 1
17
1(
#48
0(
#49
1(
#50
0(
#51
1(
#52
0(
02
06
b0 &
b0 0
0'
