Laboratorios/Lab03/TABLA3SOP/TABLA3SOP.v
module gates();
reg A, B, C,D; //declarar las 4 entradas
wire w1,w2,w3,w4,w5,w6,w7,w8,w9,w10,w11,OUT; // 4 salidas para los Not, 7 salidas para los and y una para el or final
//orden de entradas y salidas de cada compuerta
not U1(w1,A);
not U2(w2,B);
not U3(w3,C);
not U4(w4,D);
and U5(w5, w1,w2,w3,w4);
and U6(w6, w1,w2,w3,D);
and U7(w7, w1,w2,C,w4);
and U8(w8, w1,w2,C,D);
and U9(w9, A, w2, w3,w4);
and U10(w10, A,w2,C,w4);
and U11(w11, A,B,C,w4);
or  U12(OUT, w5,w6,w7,w8,w9,w10,w11);
initial begin
  $display("A B C D | Y");
  $display("--------");
  $monitor("%b %b %b %b| %b", A, B, C, D, OUT);
  A = 0; B = 0; C = 0; D = 0;
  #1 D = 1;
  #1 C = 1; D = 0;
  #1 D = 1;
  #1 B = 1; C = 0; D = 0;
  #1 D = 1;
  #1 C = 1; D = 0;
  #1 D = 1;
  #1 A = 1; B = 0; C = 0; D = 0;
  #1 D = 1;
  #1 C = 1; D = 0;
  #1 D = 1;
  #1 B = 1; C = 0; D = 0;
  #1 D = 1;
  #1 C = 1; D = 0;
  #1 D = 1;
  #1 $finish;
end

initial
  begin
    $dumpfile("TABLA3SOP_tb.vcd");
    $dumpvars(0, gates);
  end

endmodule

Digital_1/Laboratorios/Lab03/TABLA4SOP/TABLA4SOP_tb.vcd
$date
	Sat Aug 01 18:13:23 2020
$end
$version
	Icarus Verilog
$end
$timescale
	1s
$end
$scope module gates $end
$var wire 1 ! OUT $end
$var wire 1 " w1 $end
$var wire 1 # w10 $end
$var wire 1 $ w11 $end
$var wire 1 % w2 $end
$var wire 1 & w3 $end
$var wire 1 ' w4 $end
$var wire 1 ( w5 $end
$var wire 1 ) w6 $end
$var wire 1 * w7 $end
$var wire 1 + w8 $end
$var wire 1 , w9 $end
$var reg 1 - A $end
$var reg 1 . B $end
$var reg 1 / C $end
$var reg 1 0 D $end
$upscope $end
$enddefinitions $end
#0
$dumpvars
00
0/
0.
0-
0,
0+
0*
0)
1(
1'
1&
1%
0$
0#
1"
1!
$end
#1
0!
0(
0'
10
#2
1!
1)
1'
0&
00
1/
#3
0)
1*
0'
10
#4
0!
1'
0*
1&
0%
00
0/
1.
#5
0'
10
#6
1!
1+
1'
0&
00
1/
#7
0+
1,
0'
10
#8
1#
1'
1&
0,
1%
0"
00
0/
0.
1-
#9
0!
0#
0'
10
#10
1!
1$
1'
0&
00
1/
#11
0!
0$
0'
10
#12
1'
1&
0%
00
0/
1.
#13
0'
10
#14
1'
0&
00
1/
#15
0'
10
