Digital_1/Laboratorios/Lab04/ejercicio4.v
//Ejercicio 1, ecuación 1
module ejercicio1_1(input wire A, B, C, output wire OUT);
  wire w1, w2, w3, w4, w5, w6;
  not (w1, A);
  not (w2, B);
  not (w3, C);
  and (w4, w1, w3);
  and (w5, A, C);
  and (w6, A, w2);
  or (OUT, w4, w5, w6);
endmodule

//Ejercicio 1, ecuación 2
module ejercicio1_2(input wire B, output wire OUT);
  not (OUT, B);
endmodule

//Ejercicio 1, ecuación 3
module ejercicio1_3(input wire A, B, C, D, output wire OUT);
  wire w1,w2,w3,w4,w5,w6,w7,w8,w9,w10,w11,w12;
  not (w1,A);
  not (w2,B);
  not (w3,C);
  not (w4,D);
  and (w5,w1,w2,w3,w4);
  and (w6,w1,w2,C,D);
  and (w7,w1,B,C,w4);
  and (w8,A,B,w3,w4);
  and (w9,A,B,C,D);
  and (w10,A,w2,w3,D);
  and (w11,A,w2,C,w4);
  and (w12,w1,B,w3,D);
  or  (OUT,w5,w6,w7,w8,w9,w10,w11,w12);
endmodule

// Ejercicio 5 ecuacion minimizada
module ejercicio5_kmap(input wire A, B, C, output wire OUT);
  wire w1,w2;
  not (w1,B);
  or  (w2,w1,C);
  and (OUT,A,w2);
endmodule


//Ejercicio 1, ecuación 4
module ejercicio1_4(input wire A, B, C, D, output wire OUT);
  wire w1,w2,w3;
  not (w1,A);
  not (w2,D);
  or  (w3,w1,B,C,w2);
  and (OUT,A,w3);
endmodule

//Ejercicio 2, ecuación 1
module ejercicio2_1(input wire A, B, C, D, output wire OUT);
  assign  OUT = (A & ~B) | (A & C & ~D) | (A & ~C) | (~B & ~C & ~D);
endmodule

//Ejercicio 2, ecuación 2
module ejercicio2_2(input wire B, C, output wire OUT);
  assign  OUT = C | ~B;
endmodule

//Ejercicio 2, ecuación 3
module ejercicio2_3(input wire A, B, C, D, output wire OUT);
  assign  OUT = (B | D) & (A | B | ~C);
endmodule

//Ejercicio 2, ecuación 4
module ejercicio2_4(input wire A, B, C, output wire OUT);
  assign  OUT = (~A | B) & (~C | B);
endmodule
// Ejercicio 5 ecuacion POS
module ejercicio5_POS(input wire A, B, C, output wire OUT);
  assign  OUT = (A | B | C ) & (A | B |~C) & (A | ~B |C) & (A | ~B |~C) & (~A | ~B | C);
endmodule

//Ejercicio 5 ecuacion SOP
module ejercicio5_SOP(input wire A, B, C, output wire OUT);
  assign OUT = (A & ~B & ~C) | (A & ~B & C) | (A & B & C);
endmodule

Laboratorios/Lab04/ejercicio4_tb.v
`include "ejercicio4.v"

module testbench();
  reg p1, p2, p3, p4, p5, p6, p7, p8, p9, p10, p11, p12, p13, p14, p15, p16, p17;
  wire led1, led2, led3, led4, led5, led6, led7, led8, led9, led10, led11;

  ejercicio1_1 E1(p1, p2, p3, led1);
  ejercicio1_2 E2(p2,led2);
  ejercicio1_3 E3(p4, p5, p6, p7, led3);
  ejercicio1_4 E4(p4, p5, p6, p7, led4);
  ejercicio2_1 E5(p8, p9, p10, p11, led5);
  ejercicio2_3 E6(p8, p9, p10, p11, led6);
  ejercicio2_2 E7(p13, p14, led7);
  ejercicio2_4 E8(p12, p13, p14, led8);
  ejercicio5_POS  E9(p15, p16, p17, led9);
  ejercicio5_SOP  E10(p15, p16, p17, led10);
  ejercicio5_kmap E11(p15, p16, p17, led11);

  initial begin
    #1
    $display("Tabla 1.1-1.2");
    $display("A B C | Y1 Y2");
    $display("------|------");
    $monitor("%b %b %b | %b  %b", p1, p2, p3, led1, led2);
       p1 = 0; p2 = 0; p3 = 0;
    #1 p3 = 1;
    #1 p2 = 1; p3 = 0;
    #1 p3 = 1;
    #1 p1 = 1; p2 = 0; p3 = 0;
    #1 p3 = 1;
    #1 p2 = 1; p3 = 0;
    #1 p3 = 1;
  end


  initial begin
      #10
      $display("\n");
      $display(" Tabla 1.3-1.4 ");
      $display("A B C D | Y1 Y2");
      $display("--------|------");
      $monitor("%b %b %b %b | %b  %b", p4, p5, p6, p7, led3, led4);
         p4 = 0; p5 = 0; p6 = 0; p7 = 0;
      #1 p7 = 1;
      #1 p6 = 1; p7 = 0;
      #1 p7 = 1;
      #1 p5 = 1; p6 = 0; p7 = 0;
      #1 p7 = 1;
      #1 p6 = 1; p7 = 0;
      #1 p7 = 1;
      #1 p4 = 1; p5 = 0; p6 = 0; p7 = 0;
      #1 p7 = 1;
      #1 p6 = 1; p7 = 0;
      #1 p7 = 1;
      #1 p5 = 1; p6 = 0; p7 = 0;
      #1 p7 = 1;
      #1 p6 = 1; p7 = 0;
      #1 p7 = 1;
    end


  initial begin
      #26
      $display("\n");
      $display(" Tabla 2.1-2.3");
      $display("A B C D | Y1 Y2");
      $display("--------|------");
      $monitor("%b %b %b %b | %b  %b", p8, p9, p10, p11, led5, led6);
         p8 = 0; p9 = 0; p10 = 0; p11 = 0;
      #1 p11 = 1;
      #1 p10 = 1; p11 = 0;
      #1 p11 = 1;
      #1 p9 = 1; p10 = 0; p11 = 0;
      #1 p11 = 1;
      #1 p10 = 1; p11 = 0;
      #1 p11 = 1;
      #1 p8 = 1; p9 = 0; p10 = 0; p11 = 0;
      #1 p11 = 1;
      #1 p10 = 1; p11 = 0;
      #1 p11 = 1;
      #1 p9 = 1; p10 = 0; p11 = 0;
      #1 p11 = 1;
      #1 p10 = 1; p11 = 0;
      #1 p11 = 1;
    end



  initial begin
      #42
      $display("\n");
      $display("Tabla 2.2-2.4");
      $display("A B C | Y1 Y2");
      $display("------|------");
      $monitor("%b %b %b | %b  %b", p12, p13, p14, led7, led8);
         p12 = 0; p13 = 0; p14 = 0;
      #1 p14 = 1;
      #1 p13 = 1; p14 = 0;
      #1 p14 = 1;
      #1 p12 = 1; p13 = 0; p14 = 0;
      #1 p14 = 1;
      #1 p13 = 1; p14 = 0;
      #1 p14 = 1;
    end

    initial begin
        #50
        $display("\n");
        $display("Tabla 5.P-5.S-5.K");
        $display("A B C | Y1 Y2 Y3 ");
        $display("------|----------");
        $monitor("%b %b %b | %b  %b  %b", p15, p16, p17, led9, led10, led11);
           p15 = 0; p16 = 0; p17 = 0;
        #1 p17 = 1;
        #1 p16 = 1; p17 = 0;
        #1 p17 = 1;
        #1 p15 = 1; p16 = 0; p17 = 0;
        #1 p17 = 1;
        #1 p16 = 1; p17 = 0;
        #1 p17 = 1;
      end
  initial
    #58 $finish;

  initial begin
    $dumpfile("ejercicio4_tb.vcd");
    $dumpvars(0, testbench);
  end

endmodule

Laboratorios/Lab04/ejercicio4_tb.vcd
$date
	Sat Aug 08 22:22:13 2020
$end
$version
	Icarus Verilog
$end
$timescale
	1s
$end
$scope module testbench $end
$var wire 1 ! led9 $end
$var wire 1 " led8 $end
$var wire 1 # led7 $end
$var wire 1 $ led6 $end
$var wire 1 % led5 $end
$var wire 1 & led4 $end
$var wire 1 ' led3 $end
$var wire 1 ( led2 $end
$var wire 1 ) led11 $end
$var wire 1 * led10 $end
$var wire 1 + led1 $end
$var reg 1 , p1 $end
$var reg 1 - p10 $end
$var reg 1 . p11 $end
$var reg 1 / p12 $end
$var reg 1 0 p13 $end
$var reg 1 1 p14 $end
$var reg 1 2 p15 $end
$var reg 1 3 p16 $end
$var reg 1 4 p17 $end
$var reg 1 5 p2 $end
$var reg 1 6 p3 $end
$var reg 1 7 p4 $end
$var reg 1 8 p5 $end
$var reg 1 9 p6 $end
$var reg 1 : p7 $end
$var reg 1 ; p8 $end
$var reg 1 < p9 $end
$scope module E1 $end
$var wire 1 , A $end
$var wire 1 5 B $end
$var wire 1 6 C $end
$var wire 1 + OUT $end
$var wire 1 = w1 $end
$var wire 1 > w2 $end
$var wire 1 ? w3 $end
$var wire 1 @ w4 $end
$var wire 1 A w5 $end
$var wire 1 B w6 $end
$upscope $end
$scope module E10 $end
$var wire 1 2 A $end
$var wire 1 3 B $end
$var wire 1 4 C $end
$var wire 1 * OUT $end
$upscope $end
$scope module E11 $end
$var wire 1 2 A $end
$var wire 1 3 B $end
$var wire 1 4 C $end
$var wire 1 ) OUT $end
$var wire 1 C w1 $end
$var wire 1 D w2 $end
$upscope $end
$scope module E2 $end
$var wire 1 5 B $end
$var wire 1 ( OUT $end
$upscope $end
$scope module E3 $end
$var wire 1 7 A $end
$var wire 1 8 B $end
$var wire 1 9 C $end
$var wire 1 : D $end
$var wire 1 ' OUT $end
$var wire 1 E w1 $end
$var wire 1 F w10 $end
$var wire 1 G w11 $end
$var wire 1 H w12 $end
$var wire 1 I w2 $end
$var wire 1 J w3 $end
$var wire 1 K w4 $end
$var wire 1 L w5 $end
$var wire 1 M w6 $end
$var wire 1 N w7 $end
$var wire 1 O w8 $end
$var wire 1 P w9 $end
$upscope $end
$scope module E4 $end
$var wire 1 7 A $end
$var wire 1 8 B $end
$var wire 1 9 C $end
$var wire 1 : D $end
$var wire 1 & OUT $end
$var wire 1 Q w1 $end
$var wire 1 R w2 $end
$var wire 1 S w3 $end
$upscope $end
$scope module E5 $end
$var wire 1 ; A $end
$var wire 1 < B $end
$var wire 1 - C $end
$var wire 1 . D $end
$var wire 1 % OUT $end
$upscope $end
$scope module E6 $end
$var wire 1 ; A $end
$var wire 1 < B $end
$var wire 1 - C $end
$var wire 1 . D $end
$var wire 1 $ OUT $end
$upscope $end
$scope module E7 $end
$var wire 1 0 B $end
$var wire 1 1 C $end
$var wire 1 # OUT $end
$upscope $end
$scope module E8 $end
$var wire 1 / A $end
$var wire 1 0 B $end
$var wire 1 1 C $end
$var wire 1 " OUT $end
$upscope $end
$scope module E9 $end
$var wire 1 2 A $end
$var wire 1 3 B $end
$var wire 1 4 C $end
$var wire 1 ! OUT $end
$upscope $end
$upscope $end
$enddefinitions $end
#0
$dumpvars
xS
xR
xQ
xP
xO
xN
xM
xL
xK
xJ
xI
xH
xG
xF
xE
xD
xC
xB
xA
x@
x?
x>
x=
x<
x;
x:
x9
x8
x7
x6
x5
x4
x3
x2
x1
x0
x/
x.
x-
x,
x+
x*
x)
x(
x'
x&
x%
x$
x#
x"
x!
$end
#1
1+
1@
1?
1>
1(
1=
0A
0B
06
05
0,
#2
0+
0@
0?
16
#3
1+
1@
1?
0>
0(
06
15
#4
0+
0@
0?
16
#5
1+
1B
1?
1>
1(
0=
06
05
1,
#6
0?
1A
16
#7
0+
0B
1?
0A
0>
0(
06
15
#8
1+
0?
1A
16
#10
1'
1L
1K
1R
1J
0M
1I
0N
0H
1S
1E
0O
0P
0F
0G
1Q
0&
0:
09
08
07
#11
0'
0L
0K
0R
1:
#12
1K
1R
0J
0:
19
#13
1'
0K
1M
0R
1:
#14
0'
1K
1R
1J
0M
0I
0:
09
18
#15
1'
0K
1H
0R
1:
#16
1'
1N
1K
0H
1R
0J
0:
19
#17
0'
0N
0K
0R
1:
#18
1K
1R
1J
1I
1S
0E
0Q
1&
0:
09
08
17
#19
1'
0&
0S
0K
1F
0R
1:
#20
1'
1G
1&
1K
0F
1R
0J
1S
0:
19
#21
0'
0G
0K
0R
1:
#22
1'
1O
1K
1R
1J
0I
0:
09
18
#23
0'
0O
0K
0R
1:
#24
1K
1R
0J
0:
19
#25
1'
0K
1P
0R
1:
#26
1%
0$
0.
0-
0<
0;
#27
0%
1$
1.
#28
0$
0.
1-
#29
1.
#30
1$
0.
0-
1<
#31
1.
#32
0.
1-
#33
1.
#34
1%
0$
0.
0-
0<
1;
#35
1$
1.
#36
0$
0.
1-
#37
1$
1.
#38
0.
0-
1<
#39
1.
#40
1%
0.
1-
#41
0%
1.
#42
1"
1#
01
00
0/
#43
0"
11
#44
1"
0#
01
10
#45
1#
11
#46
0"
01
00
1/
#47
11
#48
1"
0#
01
10
#49
1#
11
#50
0!
0*
1D
1C
0)
04
03
02
#51
14
#52
0D
0C
04
13
#53
1D
14
#54
1*
1!
1C
1)
04
03
12
#55
14
#56
0!
0*
0)
0D
0C
04
13
#57
1*
1)
1!
1D
14
