Digital_1/Laboratorios/Lab05/Ejercicio4_5.v
//mux 2:1
module MUX2_1(input wire s1, A1, B1, output wire y1);
assign  y1 = s1?  B1: A1;
endmodule
// mux 4:1
module MUX4_1(input wire[1:0]s1, input wire A2, B2, C2, D2, output wire y2);
  wire y1, y1_2;
  MUX2_1  E1(s1[0],A2,B2,y1);
  MUX2_1  E2(s1[0],C2,D2,y1_2);
  MUX2_1  E3(s1[1],y1,y1_2,y2);
endmodule
// mux 8:1
module MUX8_1(input wire[2:0]s3, input wire A3, B3, C3, D3, E3, F3, G3, H3, output wire y3);
  wire y2, y2_2;
  MUX4_1  E1(s3[1:0],A3, B3, C3, D3,y2);
  MUX4_1  E2(s3[1:0],E3, F3, G3, H3,y2_2);
  MUX2_1  E4(s3[2],y2,y2_2,y3);
endmodule
//tabla 1 mux 8:1
module Tabla1MUX8_1 (input wire A, B, C, GND, VCC, output wire OUT);
  wire [2:0]S1;
  assign S1[0] = C;
  assign S1[1] = B;
  assign S1[2] = A;
  MUX8_1  E1(S1[2:0],GND, VCC, VCC, GND, VCC, GND, GND, VCC, OUT);
endmodule
//tabla 1 mux4:1
module Tabla1MUX4_1 (input wire A, B, C, output wire OUT);
  wire [1:0]S1;
  assign S1[0] = B;
  assign S1[1] = A;
  MUX4_1 E1(S1[1:0],C,~C, ~C, C, OUT);
endmodule
//Tabla 1 mux2:1
module Tabla1MUX2_1 (input wire A, B, C, output wire OUT);
  wire S1, W1, W2;
  assign S1 = A;
  assign W1 = B^C;
  assign W2 = ~(B^C);
  MUX2_1 E1(S1, W1, W2, OUT);
endmodule
//Tabla 2 mux 8:1
module Tabla2MUX8_1 (input wire A, B, C,GND, VCC, output wire OUT);
  wire [2:0]S1;
  assign S1[0] = C;
  assign S1[1] = B;
  assign S1[2] = A;
  MUX8_1  E1(S1[2:0],VCC,VCC,GND,GND,GND,VCC,VCC,GND,OUT);
endmodule
//Tabla 2 mux 4:1
module Tabla2MUX4_1 (input wire A, B, C,GND, output wire OUT);
  wire [1:0]S1;
  assign S1[0] = B;
  assign S1[1] = A;
  MUX4_1 E1(S1[1:0],~C,GND, C, ~C, OUT);
endmodule
//Tabla 2 mux 2:1
module Tabla2MUX2_1 (input wire A, B, C, output wire OUT);
  wire S1, W1, W2;
  assign S1 = A;
  assign W1 = ~(B | C);
  assign W2 = ~(B & C);
  MUX2_1 E1(S1, W1, W2, OUT);
endmodule

Laboratorios/Lab05/Ejercicio4_5_tb.v
`include "ejercicio4_5.v"

module testbench();
  reg p1, p2, p3;
  wire led1, led2, led3, led4, led5, led6, GND, VCC;
  assign GND = 0;
  assign VCC = 1;

  Tabla1MUX2_1  M1(p1,p2,p3,led1);
  Tabla1MUX4_1  M2(p1,p2,p3,led2);
  Tabla1MUX8_1  M3(p1,p2,p3,GND, VCC,led3);
  Tabla2MUX2_1  M4(p1,p2,p3,led4);
  Tabla2MUX4_1  M5(p1,p2,p3,GND, led5);
  Tabla2MUX8_1  M6(p1,p2,p3,GND, VCC,led6);

initial begin
#1
$display("\n");
$display(" T1MUX2:1 ");
$display("A B C | Y ");
$display("------|---");
$monitor("%b %b %b | %b ", p1,p2,p3,led1);
   p1 = 0; p2 = 0; p3 = 0;
#1 p3 = 1;
#1 p2 = 1; p3 = 0;
#1 p3 = 1;
#1 p1 = 1; p2 = 0; p3 = 0;
#1 p3 = 1;
#1 p2 = 1; p3 = 0;
#1 p3 = 1;
end

initial begin
#10
$display("\n");
$display(" T1MUX4:1 ");
$display("A B C | Y ");
$display("------|---");
$monitor("%b %b %b | %b ", p1,p2,p3,led2);
   p1 = 0; p2 = 0; p3 = 0;
#1 p3 = 1;
#1 p2 = 1; p3 = 0;
#1 p3 = 1;
#1 p1 = 1; p2 = 0; p3 = 0;
#1 p3 = 1;
#1 p2 = 1; p3 = 0;
#1 p3 = 1;
end

initial begin
#19
$display("\n");
$display(" T1MUX8:1 ");
$display("A B C | Y ");
$display("------|---");
$monitor("%b %b %b | %b ", p1,p2,p3,led3);
   p1 = 0; p2 = 0; p3 = 0;
#1 p3 = 1;
#1 p2 = 1; p3 = 0;
#1 p3 = 1;
#1 p1 = 1; p2 = 0; p3 = 0;
#1 p3 = 1;
#1 p2 = 1; p3 = 0;
#1 p3 = 1;
end

initial begin
#28
$display("\n");
$display(" T2MUX2:1 ");
$display("A B C | Y ");
$display("------|---");
$monitor("%b %b %b | %b ", p1,p2,p3,led4);
   p1 = 0; p2 = 0; p3 = 0;
#1 p3 = 1;
#1 p2 = 1; p3 = 0;
#1 p3 = 1;
#1 p1 = 1; p2 = 0; p3 = 0;
#1 p3 = 1;
#1 p2 = 1; p3 = 0;
#1 p3 = 1;
end

initial begin
#37
$display("\n");
$display(" T2MUX4:1 ");
$display("A B C | Y ");
$display("------|---");
$monitor("%b %b %b | %b ", p1,p2,p3,led5);
   p1 = 0; p2 = 0; p3 = 0;
#1 p3 = 1;
#1 p2 = 1; p3 = 0;
#1 p3 = 1;
#1 p1 = 1; p2 = 0; p3 = 0;
#1 p3 = 1;
#1 p2 = 1; p3 = 0;
#1 p3 = 1;
end

initial begin
#46
$display("\n");
$display(" T2MUX8:1 ");
$display("A B C | Y ");
$display("------|---");
$monitor("%b %b %b | %b ", p1,p2,p3,led6);
   p1 = 0; p2 = 0; p3 = 0;
#1 p3 = 1;
#1 p2 = 1; p3 = 0;
#1 p3 = 1;
#1 p1 = 1; p2 = 0; p3 = 0;
#1 p3 = 1;
#1 p2 = 1; p3 = 0;
#1 p3 = 1;
end
initial
  #55 $finish;

initial begin
  $dumpfile("ejercicio4_5_tb.vcd");
  $dumpvars(0, testbench);
end
endmodule

Laboratorios/Lab05/ejercicio4_5_tb.vcd
$date
	Sat Aug 15 17:20:59 2020
$end
$version
	Icarus Verilog
$end
$timescale
	1s
$end
$scope module testbench $end
$var wire 1 ! GND $end
$var wire 1 " VCC $end
$var wire 1 # led6 $end
$var wire 1 $ led5 $end
$var wire 1 % led4 $end
$var wire 1 & led3 $end
$var wire 1 ' led2 $end
$var wire 1 ( led1 $end
$var reg 1 ) p1 $end
$var reg 1 * p2 $end
$var reg 1 + p3 $end
$scope module M1 $end
$var wire 1 ) A $end
$var wire 1 * B $end
$var wire 1 + C $end
$var wire 1 , S1 $end
$var wire 1 - W1 $end
$var wire 1 . W2 $end
$var wire 1 ( OUT $end
$scope module E1 $end
$var wire 1 - A1 $end
$var wire 1 . B1 $end
$var wire 1 , s1 $end
$var wire 1 ( y1 $end
$upscope $end
$upscope $end
$scope module M2 $end
$var wire 1 ) A $end
$var wire 1 * B $end
$var wire 1 + C $end
$var wire 2 / S1 [1:0] $end
$var wire 1 ' OUT $end
$scope module E1 $end
$var wire 1 + A2 $end
$var wire 1 0 B2 $end
$var wire 1 1 C2 $end
$var wire 1 + D2 $end
$var wire 2 2 s1 [1:0] $end
$var wire 1 ' y2 $end
$var wire 1 3 y1_2 $end
$var wire 1 4 y1 $end
$scope module E1 $end
$var wire 1 + A1 $end
$var wire 1 0 B1 $end
$var wire 1 5 s1 $end
$var wire 1 4 y1 $end
$upscope $end
$scope module E2 $end
$var wire 1 1 A1 $end
$var wire 1 + B1 $end
$var wire 1 6 s1 $end
$var wire 1 3 y1 $end
$upscope $end
$scope module E3 $end
$var wire 1 4 A1 $end
$var wire 1 3 B1 $end
$var wire 1 7 s1 $end
$var wire 1 ' y1 $end
$upscope $end
$upscope $end
$upscope $end
$scope module M3 $end
$var wire 1 ) A $end
$var wire 1 * B $end
$var wire 1 + C $end
$var wire 1 ! GND $end
$var wire 1 " VCC $end
$var wire 3 8 S1 [2:0] $end
$var wire 1 & OUT $end
$scope module E1 $end
$var wire 1 ! A3 $end
$var wire 1 " B3 $end
$var wire 1 " C3 $end
$var wire 1 ! D3 $end
$var wire 1 " E3 $end
$var wire 1 ! F3 $end
$var wire 1 ! G3 $end
$var wire 1 " H3 $end
$var wire 3 9 s3 [2:0] $end
$var wire 1 & y3 $end
$var wire 1 : y2_2 $end
$var wire 1 ; y2 $end
$scope module E1 $end
$var wire 1 ! A2 $end
$var wire 1 " B2 $end
$var wire 1 " C2 $end
$var wire 1 ! D2 $end
$var wire 2 < s1 [1:0] $end
$var wire 1 ; y2 $end
$var wire 1 = y1_2 $end
$var wire 1 > y1 $end
$scope module E1 $end
$var wire 1 ! A1 $end
$var wire 1 " B1 $end
$var wire 1 ? s1 $end
$var wire 1 > y1 $end
$upscope $end
$scope module E2 $end
$var wire 1 " A1 $end
$var wire 1 ! B1 $end
$var wire 1 @ s1 $end
$var wire 1 = y1 $end
$upscope $end
$scope module E3 $end
$var wire 1 > A1 $end
$var wire 1 = B1 $end
$var wire 1 A s1 $end
$var wire 1 ; y1 $end
$upscope $end
$upscope $end
$scope module E2 $end
$var wire 1 " A2 $end
$var wire 1 ! B2 $end
$var wire 1 ! C2 $end
$var wire 1 " D2 $end
$var wire 2 B s1 [1:0] $end
$var wire 1 : y2 $end
$var wire 1 C y1_2 $end
$var wire 1 D y1 $end
$scope module E1 $end
$var wire 1 " A1 $end
$var wire 1 ! B1 $end
$var wire 1 E s1 $end
$var wire 1 D y1 $end
$upscope $end
$scope module E2 $end
$var wire 1 ! A1 $end
$var wire 1 " B1 $end
$var wire 1 F s1 $end
$var wire 1 C y1 $end
$upscope $end
$scope module E3 $end
$var wire 1 D A1 $end
$var wire 1 C B1 $end
$var wire 1 G s1 $end
$var wire 1 : y1 $end
$upscope $end
$upscope $end
$scope module E4 $end
$var wire 1 ; A1 $end
$var wire 1 : B1 $end
$var wire 1 H s1 $end
$var wire 1 & y1 $end
$upscope $end
$upscope $end
$upscope $end
$scope module M4 $end
$var wire 1 ) A $end
$var wire 1 * B $end
$var wire 1 + C $end
$var wire 1 I S1 $end
$var wire 1 J W1 $end
$var wire 1 K W2 $end
$var wire 1 % OUT $end
$scope module E1 $end
$var wire 1 J A1 $end
$var wire 1 K B1 $end
$var wire 1 I s1 $end
$var wire 1 % y1 $end
$upscope $end
$upscope $end
$scope module M5 $end
$var wire 1 ) A $end
$var wire 1 * B $end
$var wire 1 + C $end
$var wire 1 ! GND $end
$var wire 2 L S1 [1:0] $end
$var wire 1 $ OUT $end
$scope module E1 $end
$var wire 1 M A2 $end
$var wire 1 ! B2 $end
$var wire 1 + C2 $end
$var wire 1 N D2 $end
$var wire 2 O s1 [1:0] $end
$var wire 1 $ y2 $end
$var wire 1 P y1_2 $end
$var wire 1 Q y1 $end
$scope module E1 $end
$var wire 1 M A1 $end
$var wire 1 ! B1 $end
$var wire 1 R s1 $end
$var wire 1 Q y1 $end
$upscope $end
$scope module E2 $end
$var wire 1 + A1 $end
$var wire 1 N B1 $end
$var wire 1 S s1 $end
$var wire 1 P y1 $end
$upscope $end
$scope module E3 $end
$var wire 1 Q A1 $end
$var wire 1 P B1 $end
$var wire 1 T s1 $end
$var wire 1 $ y1 $end
$upscope $end
$upscope $end
$upscope $end
$scope module M6 $end
$var wire 1 ) A $end
$var wire 1 * B $end
$var wire 1 + C $end
$var wire 1 ! GND $end
$var wire 1 " VCC $end
$var wire 3 U S1 [2:0] $end
$var wire 1 # OUT $end
$scope module E1 $end
$var wire 1 " A3 $end
$var wire 1 " B3 $end
$var wire 1 ! C3 $end
$var wire 1 ! D3 $end
$var wire 1 ! E3 $end
$var wire 1 " F3 $end
$var wire 1 " G3 $end
$var wire 1 ! H3 $end
$var wire 3 V s3 [2:0] $end
$var wire 1 # y3 $end
$var wire 1 W y2_2 $end
$var wire 1 X y2 $end
$scope module E1 $end
$var wire 1 " A2 $end
$var wire 1 " B2 $end
$var wire 1 ! C2 $end
$var wire 1 ! D2 $end
$var wire 2 Y s1 [1:0] $end
$var wire 1 X y2 $end
$var wire 1 Z y1_2 $end
$var wire 1 [ y1 $end
$scope module E1 $end
$var wire 1 " A1 $end
$var wire 1 " B1 $end
$var wire 1 \ s1 $end
$var wire 1 [ y1 $end
$upscope $end
$scope module E2 $end
$var wire 1 ! A1 $end
$var wire 1 ! B1 $end
$var wire 1 ] s1 $end
$var wire 1 Z y1 $end
$upscope $end
$scope module E3 $end
$var wire 1 [ A1 $end
$var wire 1 Z B1 $end
$var wire 1 ^ s1 $end
$var wire 1 X y1 $end
$upscope $end
$upscope $end
$scope module E2 $end
$var wire 1 ! A2 $end
$var wire 1 " B2 $end
$var wire 1 " C2 $end
$var wire 1 ! D2 $end
$var wire 2 _ s1 [1:0] $end
$var wire 1 W y2 $end
$var wire 1 ` y1_2 $end
$var wire 1 a y1 $end
$scope module E1 $end
$var wire 1 ! A1 $end
$var wire 1 " B1 $end
$var wire 1 b s1 $end
$var wire 1 a y1 $end
$upscope $end
$scope module E2 $end
$var wire 1 " A1 $end
$var wire 1 ! B1 $end
$var wire 1 c s1 $end
$var wire 1 ` y1 $end
$upscope $end
$scope module E3 $end
$var wire 1 a A1 $end
$var wire 1 ` B1 $end
$var wire 1 d s1 $end
$var wire 1 W y1 $end
$upscope $end
$upscope $end
$scope module E4 $end
$var wire 1 X A1 $end
$var wire 1 W B1 $end
$var wire 1 e s1 $end
$var wire 1 # y1 $end
$upscope $end
$upscope $end
$upscope $end
$upscope $end
$enddefinitions $end
#0
$dumpvars
xe
xd
xc
xb
xa
x`
bx _
x^
x]
x\
1[
0Z
bx Y
xX
xW
bx V
bx U
xT
xS
xR
xQ
xP
bx O
xN
xM
bx L
xK
xJ
xI
xH
xG
xF
xE
xD
xC
bx B
xA
x@
x?
x>
x=
bx <
x;
x:
bx 9
bx 8
x7
x6
x5
x4
x3
bx 2
x1
x0
bx /
x.
x-
x,
x+
x*
x)
x(
x'
x&
x%
x$
x#
1"
0!
$end
#1
0&
0;
1:
1#
0W
0>
1=
1D
0C
1%
1$
1X
0a
1`
13
0(
1.
0?
0@
0A
0E
0F
0G
1J
1K
1Q
0\
0]
0^
0b
0c
0d
0'
10
11
04
1M
1N
0P
0-
05
06
b0 <
b0 B
0R
0S
b0 Y
b0 _
07
0H
0T
0e
0+
0*
0,
b0 /
b0 2
b0 8
b0 9
0I
b0 L
b0 O
b0 U
b0 V
0)
#2
1&
1;
0:
1W
1>
0=
0D
1C
0%
0$
1a
0`
1(
0.
03
1'
1?
1@
1E
1F
0J
0Q
1\
1]
1b
1c
1-
00
01
14
b1 <
b1 B
0M
0N
1P
b1 Y
b1 _
b1 8
b1 9
b1 U
b1 V
1+
#3
1&
0#
0>
1=
1;
1D
0C
0:
0X
0a
1`
1W
1'
0?
0@
1A
0E
0F
1G
0\
0]
1^
0b
0c
1d
10
11
14
1M
1N
1P
15
16
b10 <
b10 B
1R
1S
b10 Y
b10 _
0+
b1 /
b1 2
b10 8
b10 9
b1 L
b1 O
b10 U
b10 V
1*
#4
0&
0;
1:
0W
0'
1>
0=
0D
1C
1a
0`
0(
1.
04
1?
1@
1E
1F
0K
0P
1\
1]
1b
1c
0-
00
01
13
b11 <
b11 B
0M
0N
b11 Y
b11 _
b11 8
b11 9
b11 U
b11 V
1+
#5
0#
1'
0>
1=
0;
1D
0C
1:
1%
1X
0a
1`
0W
0?
0@
0A
0E
0F
0G
1J
1K
1Q
0\
0]
0^
0b
0c
0d
1&
10
11
13
1M
1N
05
06
b0 <
b0 B
0R
0S
b0 Y
b0 _
1(
17
1H
1T
1e
0+
0*
1,
b10 /
b10 2
b100 8
b100 9
1I
b10 L
b10 O
b100 U
b100 V
1)
#6
0&
1#
1;
0:
1W
0(
0'
1>
0=
0D
1C
1a
0`
0.
03
1?
1@
1E
1F
0J
0Q
1$
1\
1]
1b
1c
1-
00
01
14
b1 <
b1 B
0M
0N
1P
b1 Y
b1 _
b101 8
b101 9
b101 U
b101 V
1+
#7
0&
1#
0>
1=
1;
1D
0C
0:
0X
0a
1`
1W
1$
0?
0@
1A
0E
0F
1G
0\
0]
1^
0b
0c
1d
10
11
14
1M
1N
1P
15
16
b10 <
b10 B
1R
1S
b10 Y
b10 _
0+
b11 /
b11 2
b110 8
b110 9
b11 L
b11 O
b110 U
b110 V
1*
#8
1&
0#
0;
1:
0W
1(
1>
0=
0D
1C
0%
0$
1a
0`
1.
04
1'
1?
1@
1E
1F
0K
0P
1\
1]
1b
1c
0-
00
01
13
b11 <
b11 B
0M
0N
b11 Y
b11 _
b111 8
b111 9
b111 U
b111 V
1+
#10
1#
0>
1=
0;
1D
0C
1:
1%
1$
1X
0a
1`
0W
0?
0@
0A
0E
0F
0G
1J
1K
1Q
0\
0]
0^
0b
0c
0d
0'
0&
10
11
13
1M
1N
05
06
b0 <
b0 B
0R
0S
b0 Y
b0 _
0(
07
0H
0T
0e
0+
0*
0,
b0 /
b0 2
b0 8
b0 9
0I
b0 L
b0 O
b0 U
b0 V
0)
#11
1&
1;
0:
1W
1>
0=
0D
1C
0%
0$
1a
0`
1(
0.
03
1'
1?
1@
1E
1F
0J
0Q
1\
1]
1b
1c
1-
00
01
14
b1 <
b1 B
0M
0N
1P
b1 Y
b1 _
b1 8
b1 9
b1 U
b1 V
1+
#12
1&
0#
0>
1=
1;
1D
0C
0:
0X
0a
1`
1W
1'
0?
0@
1A
0E
0F
1G
0\
0]
1^
0b
0c
1d
10
11
14
1M
1N
1P
15
16
b10 <
b10 B
1R
1S
b10 Y
b10 _
0+
b1 /
b1 2
b10 8
b10 9
b1 L
b1 O
b10 U
b10 V
1*
#13
0&
0;
1:
0W
0'
1>
0=
0D
1C
1a
0`
0(
1.
04
1?
1@
1E
1F
0K
0P
1\
1]
1b
1c
0-
00
01
13
b11 <
b11 B
0M
0N
b11 Y
b11 _
b11 8
b11 9
b11 U
b11 V
1+
#14
0#
1'
0>
1=
0;
1D
0C
1:
1%
1X
0a
1`
0W
0?
0@
0A
0E
0F
0G
1J
1K
1Q
0\
0]
0^
0b
0c
0d
1&
10
11
13
1M
1N
05
06
b0 <
b0 B
0R
0S
b0 Y
b0 _
1(
17
1H
1T
1e
0+
0*
1,
b10 /
b10 2
b100 8
b100 9
1I
b10 L
b10 O
b100 U
b100 V
1)
#15
0&
1#
1;
0:
1W
0(
0'
1>
0=
0D
1C
1a
0`
0.
03
1?
1@
1E
1F
0J
0Q
1$
1\
1]
1b
1c
1-
00
01
14
b1 <
b1 B
0M
0N
1P
b1 Y
b1 _
b101 8
b101 9
b101 U
b101 V
1+
#16
0&
1#
0>
1=
1;
1D
0C
0:
0X
0a
1`
1W
1$
0?
0@
1A
0E
0F
1G
0\
0]
1^
0b
0c
1d
10
11
14
1M
1N
1P
15
16
b10 <
b10 B
1R
1S
b10 Y
b10 _
0+
b11 /
b11 2
b110 8
b110 9
b11 L
b11 O
b110 U
b110 V
1*
#17
1&
0#
0;
1:
0W
1(
1>
0=
0D
1C
0%
0$
1a
0`
1.
04
1'
1?
1@
1E
1F
0K
0P
1\
1]
1b
1c
0-
00
01
13
b11 <
b11 B
0M
0N
b11 Y
b11 _
b111 8
b111 9
b111 U
b111 V
1+
#19
1#
0>
1=
0;
1D
0C
1:
1%
1$
1X
0a
1`
0W
0?
0@
0A
0E
0F
0G
1J
1K
1Q
0\
0]
0^
0b
0c
0d
0'
0&
10
11
13
1M
1N
05
06
b0 <
b0 B
0R
0S
b0 Y
b0 _
0(
07
0H
0T
0e
0+
0*
0,
b0 /
b0 2
b0 8
b0 9
0I
b0 L
b0 O
b0 U
b0 V
0)
#20
1&
1;
0:
1W
1>
0=
0D
1C
0%
0$
1a
0`
1(
0.
03
1'
1?
1@
1E
1F
0J
0Q
1\
1]
1b
1c
1-
00
01
14
b1 <
b1 B
0M
0N
1P
b1 Y
b1 _
b1 8
b1 9
b1 U
b1 V
1+
#21
1&
0#
0>
1=
1;
1D
0C
0:
0X
0a
1`
1W
1'
0?
0@
1A
0E
0F
1G
0\
0]
1^
0b
0c
1d
10
11
14
1M
1N
1P
15
16
b10 <
b10 B
1R
1S
b10 Y
b10 _
0+
b1 /
b1 2
b10 8
b10 9
b1 L
b1 O
b10 U
b10 V
1*
#22
0&
0;
1:
0W
0'
1>
0=
0D
1C
1a
0`
0(
1.
04
1?
1@
1E
1F
0K
0P
1\
1]
1b
1c
0-
00
01
13
b11 <
b11 B
0M
0N
b11 Y
b11 _
b11 8
b11 9
b11 U
b11 V
1+
#23
0#
1'
0>
1=
0;
1D
0C
1:
1%
1X
0a
1`
0W
0?
0@
0A
0E
0F
0G
1J
1K
1Q
0\
0]
0^
0b
0c
0d
1&
10
11
13
1M
1N
05
06
b0 <
b0 B
0R
0S
b0 Y
b0 _
1(
17
1H
1T
1e
0+
0*
1,
b10 /
b10 2
b100 8
b100 9
1I
b10 L
b10 O
b100 U
b100 V
1)
#24
0&
1#
1;
0:
1W
0(
0'
1>
0=
0D
1C
1a
0`
0.
03
1?
1@
1E
1F
0J
0Q
1$
1\
1]
1b
1c
1-
00
01
14
b1 <
b1 B
0M
0N
1P
b1 Y
b1 _
b101 8
b101 9
b101 U
b101 V
1+
#25
0&
1#
0>
1=
1;
1D
0C
0:
0X
0a
1`
1W
1$
0?
0@
1A
0E
0F
1G
0\
0]
1^
0b
0c
1d
10
11
14
1M
1N
1P
15
16
b10 <
b10 B
1R
1S
b10 Y
b10 _
0+
b11 /
b11 2
b110 8
b110 9
b11 L
b11 O
b110 U
b110 V
1*
#26
1&
0#
0;
1:
0W
1(
1>
0=
0D
1C
0%
0$
1a
0`
1.
04
1'
1?
1@
1E
1F
0K
0P
1\
1]
1b
1c
0-
00
01
13
b11 <
b11 B
0M
0N
b11 Y
b11 _
b111 8
b111 9
b111 U
b111 V
1+
#28
1#
0>
1=
0;
1D
0C
1:
1%
1$
1X
0a
1`
0W
0?
0@
0A
0E
0F
0G
1J
1K
1Q
0\
0]
0^
0b
0c
0d
0'
0&
10
11
13
1M
1N
05
06
b0 <
b0 B
0R
0S
b0 Y
b0 _
0(
07
0H
0T
0e
0+
0*
0,
b0 /
b0 2
b0 8
b0 9
0I
b0 L
b0 O
b0 U
b0 V
0)
#29
1&
1;
0:
1W
1>
0=
0D
1C
0%
0$
1a
0`
1(
0.
03
1'
1?
1@
1E
1F
0J
0Q
1\
1]
1b
1c
1-
00
01
14
b1 <
b1 B
0M
0N
1P
b1 Y
b1 _
b1 8
b1 9
b1 U
b1 V
1+
#30
1&
0#
0>
1=
1;
1D
0C
0:
0X
0a
1`
1W
1'
0?
0@
1A
0E
0F
1G
0\
0]
1^
0b
0c
1d
10
11
14
1M
1N
1P
15
16
b10 <
b10 B
1R
1S
b10 Y
b10 _
0+
b1 /
b1 2
b10 8
b10 9
b1 L
b1 O
b10 U
b10 V
1*
#31
0&
0;
1:
0W
0'
1>
0=
0D
1C
1a
0`
0(
1.
04
1?
1@
1E
1F
0K
0P
1\
1]
1b
1c
0-
00
01
13
b11 <
b11 B
0M
0N
b11 Y
b11 _
b11 8
b11 9
b11 U
b11 V
1+
#32
0#
1'
0>
1=
0;
1D
0C
1:
1%
1X
0a
1`
0W
0?
0@
0A
0E
0F
0G
1J
1K
1Q
0\
0]
0^
0b
0c
0d
1&
10
11
13
1M
1N
05
06
b0 <
b0 B
0R
0S
b0 Y
b0 _
1(
17
1H
1T
1e
0+
0*
1,
b10 /
b10 2
b100 8
b100 9
1I
b10 L
b10 O
b100 U
b100 V
1)
#33
0&
1#
1;
0:
1W
0(
0'
1>
0=
0D
1C
1a
0`
0.
03
1?
1@
1E
1F
0J
0Q
1$
1\
1]
1b
1c
1-
00
01
14
b1 <
b1 B
0M
0N
1P
b1 Y
b1 _
b101 8
b101 9
b101 U
b101 V
1+
#34
0&
1#
0>
1=
1;
1D
0C
0:
0X
0a
1`
1W
1$
0?
0@
1A
0E
0F
1G
0\
0]
1^
0b
0c
1d
10
11
14
1M
1N
1P
15
16
b10 <
b10 B
1R
1S
b10 Y
b10 _
0+
b11 /
b11 2
b110 8
b110 9
b11 L
b11 O
b110 U
b110 V
1*
#35
1&
0#
0;
1:
0W
1(
1>
0=
0D
1C
0%
0$
1a
0`
1.
04
1'
1?
1@
1E
1F
0K
0P
1\
1]
1b
1c
0-
00
01
13
b11 <
b11 B
0M
0N
b11 Y
b11 _
b111 8
b111 9
b111 U
b111 V
1+
#37
1#
0>
1=
0;
1D
0C
1:
1%
1$
1X
0a
1`
0W
0?
0@
0A
0E
0F
0G
1J
1K
1Q
0\
0]
0^
0b
0c
0d
0'
0&
10
11
13
1M
1N
05
06
b0 <
b0 B
0R
0S
b0 Y
b0 _
0(
07
0H
0T
0e
0+
0*
0,
b0 /
b0 2
b0 8
b0 9
0I
b0 L
b0 O
b0 U
b0 V
0)
#38
1&
1;
0:
1W
1>
0=
0D
1C
0%
0$
1a
0`
1(
0.
03
1'
1?
1@
1E
1F
0J
0Q
1\
1]
1b
1c
1-
00
01
14
b1 <
b1 B
0M
0N
1P
b1 Y
b1 _
b1 8
b1 9
b1 U
b1 V
1+
#39
1&
0#
0>
1=
1;
1D
0C
0:
0X
0a
1`
1W
1'
0?
0@
1A
0E
0F
1G
0\
0]
1^
0b
0c
1d
10
11
14
1M
1N
1P
15
16
b10 <
b10 B
1R
1S
b10 Y
b10 _
0+
b1 /
b1 2
b10 8
b10 9
b1 L
b1 O
b10 U
b10 V
1*
#40
0&
0;
1:
0W
0'
1>
0=
0D
1C
1a
0`
0(
1.
04
1?
1@
1E
1F
0K
0P
1\
1]
1b
1c
0-
00
01
13
b11 <
b11 B
0M
0N
b11 Y
b11 _
b11 8
b11 9
b11 U
b11 V
1+
#41
0#
1'
0>
1=
0;
1D
0C
1:
1%
1X
0a
1`
0W
0?
0@
0A
0E
0F
0G
1J
1K
1Q
0\
0]
0^
0b
0c
0d
1&
10
11
13
1M
1N
05
06
b0 <
b0 B
0R
0S
b0 Y
b0 _
1(
17
1H
1T
1e
0+
0*
1,
b10 /
b10 2
b100 8
b100 9
1I
b10 L
b10 O
b100 U
b100 V
1)
#42
0&
1#
1;
0:
1W
0(
0'
1>
0=
0D
1C
1a
0`
0.
03
1?
1@
1E
1F
0J
0Q
1$
1\
1]
1b
1c
1-
00
01
14
b1 <
b1 B
0M
0N
1P
b1 Y
b1 _
b101 8
b101 9
b101 U
b101 V
1+
#43
0&
1#
0>
1=
1;
1D
0C
0:
0X
0a
1`
1W
1$
0?
0@
1A
0E
0F
1G
0\
0]
1^
0b
0c
1d
10
11
14
1M
1N
1P
15
16
b10 <
b10 B
1R
1S
b10 Y
b10 _
0+
b11 /
b11 2
b110 8
b110 9
b11 L
b11 O
b110 U
b110 V
1*
#44
1&
0#
0;
1:
0W
1(
1>
0=
0D
1C
0%
0$
1a
0`
1.
04
1'
1?
1@
1E
1F
0K
0P
1\
1]
1b
1c
0-
00
01
13
b11 <
b11 B
0M
0N
b11 Y
b11 _
b111 8
b111 9
b111 U
b111 V
1+
#46
1#
0>
1=
0;
1D
0C
1:
1%
1$
1X
0a
1`
0W
0?
0@
0A
0E
0F
0G
1J
1K
1Q
0\
0]
0^
0b
0c
0d
0'
0&
10
11
13
1M
1N
05
06
b0 <
b0 B
0R
0S
b0 Y
b0 _
0(
07
0H
0T
0e
0+
0*
0,
b0 /
b0 2
b0 8
b0 9
0I
b0 L
b0 O
b0 U
b0 V
0)
#47
1&
1;
0:
1W
1>
0=
0D
1C
0%
0$
1a
0`
1(
0.
03
1'
1?
1@
1E
1F
0J
0Q
1\
1]
1b
1c
1-
00
01
14
b1 <
b1 B
0M
0N
1P
b1 Y
b1 _
b1 8
b1 9
b1 U
b1 V
1+
#48
1&
0#
0>
1=
1;
1D
0C
0:
0X
0a
1`
1W
1'
0?
0@
1A
0E
0F
1G
0\
0]
1^
0b
0c
1d
10
11
14
1M
1N
1P
15
16
b10 <
b10 B
1R
1S
b10 Y
b10 _
0+
b1 /
b1 2
b10 8
b10 9
b1 L
b1 O
b10 U
b10 V
1*
#49
0&
0;
1:
0W
0'
1>
0=
0D
1C
1a
0`
0(
1.
04
1?
1@
1E
1F
0K
0P
1\
1]
1b
1c
0-
00
01
13
b11 <
b11 B
0M
0N
b11 Y
b11 _
b11 8
b11 9
b11 U
b11 V
1+
#50
0#
1'
0>
1=
0;
1D
0C
1:
1%
1X
0a
1`
0W
0?
0@
0A
0E
0F
0G
1J
1K
1Q
0\
0]
0^
0b
0c
0d
1&
10
11
13
1M
1N
05
06
b0 <
b0 B
0R
0S
b0 Y
b0 _
1(
17
1H
1T
1e
0+
0*
1,
b10 /
b10 2
b100 8
b100 9
1I
b10 L
b10 O
b100 U
b100 V
1)
#51
0&
1#
1;
0:
1W
0(
0'
1>
0=
0D
1C
1a
0`
0.
03
1?
1@
1E
1F
0J
0Q
1$
1\
1]
1b
1c
1-
00
01
14
b1 <
b1 B
0M
0N
1P
b1 Y
b1 _
b101 8
b101 9
b101 U
b101 V
1+
#52
0&
1#
0>
1=
1;
1D
0C
0:
0X
0a
1`
1W
1$
0?
0@
1A
0E
0F
1G
0\
0]
1^
0b
0c
1d
10
11
14
1M
1N
1P
15
16
b10 <
b10 B
1R
1S
b10 Y
b10 _
0+
b11 /
b11 2
b110 8
b110 9
b11 L
b11 O
b110 U
b110 V
1*
#53
1&
0#
0;
1:
0W
1(
1>
0=
0D
1C
0%
0$
1a
0`
1.
04
1'
1?
1@
1E
1F
0K
0P
1\
1]
1b
1c
0-
00
01
13
b11 <
b11 B
0M
0N
b11 Y
b11 _
b111 8
b111 9
b111 U
b111 V
1+
