Laboratorios/Lab08/contador.v
//modulo de contador con enable reset y clock, tiene la opcion de cargar el valor del load_1 al count al momento de activar el bit load o que load_1 tenga un cambio
module contador (input wire clock, reset, load, en, input wire [11:0]load_1, output reg [11:0]count);
  always @ (posedge clock or posedge reset or load or load_1) begin
      if (reset) begin
      count <= 12'b000000000000;
      end
      else if (load) begin
      count <= load_1;
      end
      else if (en) begin
      count <= count + 12'b000000000001;
      end
      end
      endmodule
//arreglo de memoria de 4kx8bits a la cual cargue los valores ingresados en ROM.list
module ROM (input wire[11:0]address, output wire [7:0]palabra);
  reg [7:0] array [0:4095];
    initial begin
    $readmemh("ROM.list", array);
    end
    assign palabra = array[address];
    endmodule
//ALU de 4 bits implementada con cases
module ALU (input wire [3:0]A, B, input wire [2:0]S, output reg [3:0]resultado);
  always @ (*) begin
    case(S)
    0:
    resultado <= A & B;
    1:
    resultado <= A | B;
    2:
    resultado <= A + B;
    3:
    resultado <= 4'b0;
    4:
    resultado <= A & ~B;
    5:
    resultado <= A | ~B;
    6:
    resultado <= A - B;
    7:
    resultado <= (A < B) ? 4'b1111: 4'b0;
    default:
    resultado <= 4'b0;
    endcase
    end
    endmodule

Laboratorios/Lab08/ROM_tb.v
`include "contador.v"
module testbench();
reg [11:0]address;
wire [7:0]palabra;
ROM E1 (address, palabra);

  initial begin
  #1
  $display(" MEMORIA ROM");
  $display("    ADRESS   |   PALABRA  ");
  $display("-------------|------------");
  $monitor("%b | %b " ,address, palabra);
  end
  initial begin
  address = 12'b000000000000;
#3 address = 12'b000000000001;
#3 address = 12'b000001010101;
#3 address = 12'b000001010110;
#3 address = 12'b000001010111;
#3 address = 12'b000001011000;
#3 address = 12'b000010001000;
#3 address = 12'b000010001001;
#3 address = 12'b000010001010;
#3 address = 12'b000010001011;
  end

  initial
    #50 $finish;
  initial begin
      $dumpfile("ROM_tb.vcd");
      $dumpvars(0, testbench);
    end
  endmodule

Laboratorios/Lab08/ROM_tb.vcd
$date
	Fri Oct 23 21:02:36 2020
$end
$version
	Icarus Verilog
$end
$timescale
	1s
$end
$scope module testbench $end
$var wire 8 ! palabra [7:0] $end
$var reg 12 " address [11:0] $end
$scope module E1 $end
$var wire 12 # address [11:0] $end
$var wire 8 $ palabra [7:0] $end
$upscope $end
$upscope $end
$enddefinitions $end
#0
$dumpvars
b1 $
b0 #
b0 "
b1 !
$end
#3
b10 !
b10 $
b1 "
b1 #
#6
b1010101 !
b1010101 $
b1010101 "
b1010101 #
#9
b1010110 !
b1010110 $
b1010110 "
b1010110 #
#12
b1010111 !
b1010111 $
b1010111 "
b1010111 #
#15
b1011000 !
b1011000 $
b1011000 "
b1011000 #
#18
b10001000 !
b10001000 $
b10001000 "
b10001000 #
#21
b10001001 !
b10001001 $
b10001001 "
b10001001 #
#24
b10001010 !
b10001010 $
b10001010 "
b10001010 #
#27
b10001011 !
b10001011 $
b10001011 "
b10001011 #
